{"@t":"2024-04-18T11:16:22.8631694Z","@mt":"{StartMessage} [Timing {TimingId}]","StartMessage":"Booting Umbraco 8.12.2.","TimingId":"3966b3c","SourceContext":"Umbraco.Core.Runtime.CoreRuntime","ProcessId":7208,"ProcessName":"iisexpress","ThreadId":1,"AppDomainId":2,"AppDomainAppId":"LMW3SVC2ROOT","MachineName":"WKWIN4480425","Log4NetLevel":"INFO ","HttpRequestNumber":1,"HttpRequestId":"90fe43c2-132e-45c4-97bc-490d8fec026c"}
{"@t":"2024-04-18T11:16:22.8930900Z","@mt":"Booting site '{HostingSiteName}', app '{HostingApplicationID}', path '{HostingPhysicalPath}', server '{MachineName}'.","HostingSiteName":"HPPlc","HostingApplicationID":"/LM/W3SVC/2/ROOT","HostingPhysicalPath":"C:\\Projects\\HP Proj\\HP PLC\\Preprod\\HPPlc_PreProd_Index_BW_Live\\HPPlc\\","MachineName":"WKWIN4480425","SourceContext":"Umbraco.Core.Runtime.CoreRuntime","ProcessId":7208,"ProcessName":"iisexpress","ThreadId":1,"AppDomainId":2,"AppDomainAppId":"LMW3SVC2ROOT","Log4NetLevel":"INFO ","HttpRequestNumber":1,"HttpRequestId":"90fe43c2-132e-45c4-97bc-490d8fec026c"}
{"@t":"2024-04-18T11:16:23.0057132Z","@mt":"Acquiring.","SourceContext":"Umbraco.Core.Runtime.MainDom","ProcessId":7208,"ProcessName":"iisexpress","ThreadId":1,"AppDomainId":2,"AppDomainAppId":"LMW3SVC2ROOT","MachineName":"WKWIN4480425","Log4NetLevel":"INFO ","HttpRequestNumber":1,"HttpRequestId":"90fe43c2-132e-45c4-97bc-490d8fec026c"}
{"@t":"2024-04-18T11:16:23.0077081Z","@mt":"Acquired.","SourceContext":"Umbraco.Core.Runtime.MainDom","ProcessId":7208,"ProcessName":"iisexpress","ThreadId":1,"AppDomainId":2,"AppDomainAppId":"LMW3SVC2ROOT","MachineName":"WKWIN4480425","Log4NetLevel":"INFO ","HttpRequestNumber":1,"HttpRequestId":"90fe43c2-132e-45c4-97bc-490d8fec026c"}
{"@t":"2024-04-18T11:16:24.7235106Z","@mt":"{StartMessage} [Timing {TimingId}]","StartMessage":"Resolving composer types.","TimingId":"f40b4ff","SourceContext":"Umbraco.Core.Runtime.CoreRuntime","ProcessId":7208,"ProcessName":"iisexpress","ThreadId":1,"AppDomainId":2,"AppDomainAppId":"LMW3SVC2ROOT","MachineName":"WKWIN4480425","Log4NetLevel":"INFO ","HttpRequestNumber":1,"HttpRequestId":"90fe43c2-132e-45c4-97bc-490d8fec026c"}
{"@t":"2024-04-18T11:16:25.0795986Z","@mt":"{EndMessage} ({Duration}ms) [Timing {TimingId}]","EndMessage":"Resolved.","Duration":353,"TimingId":"f40b4ff","SourceContext":"Umbraco.Core.Runtime.CoreRuntime","ProcessId":7208,"ProcessName":"iisexpress","ThreadId":1,"AppDomainId":2,"AppDomainAppId":"LMW3SVC2ROOT","MachineName":"WKWIN4480425","Log4NetLevel":"INFO ","HttpRequestNumber":1,"HttpRequestId":"90fe43c2-132e-45c4-97bc-490d8fec026c"}
{"@t":"2024-04-18T11:16:26.5522492Z","@mt":"Registered with MainDom, localContentDbExists? {LocalContentDbExists}, localMediaDbExists? {LocalMediaDbExists}","LocalContentDbExists":true,"LocalMediaDbExists":true,"SourceContext":"Umbraco.Web.PublishedCache.NuCache.PublishedSnapshotService","ProcessId":7208,"ProcessName":"iisexpress","ThreadId":1,"AppDomainId":2,"AppDomainAppId":"LMW3SVC2ROOT","MachineName":"WKWIN4480425","Log4NetLevel":"INFO ","HttpRequestNumber":1,"HttpRequestId":"90fe43c2-132e-45c4-97bc-490d8fec026c"}
{"@t":"2024-04-18T11:16:26.5522492Z","@mt":"Creating the content store, localContentDbExists? {LocalContentDbExists}","LocalContentDbExists":true,"SourceContext":"Umbraco.Web.PublishedCache.NuCache.PublishedSnapshotService","ProcessId":7208,"ProcessName":"iisexpress","ThreadId":1,"AppDomainId":2,"AppDomainAppId":"LMW3SVC2ROOT","MachineName":"WKWIN4480425","Log4NetLevel":"INFO ","HttpRequestNumber":1,"HttpRequestId":"90fe43c2-132e-45c4-97bc-490d8fec026c"}
{"@t":"2024-04-18T11:16:26.5562387Z","@mt":"Creating the media store, localMediaDbExists? {LocalMediaDbExists}","LocalMediaDbExists":true,"SourceContext":"Umbraco.Web.PublishedCache.NuCache.PublishedSnapshotService","ProcessId":7208,"ProcessName":"iisexpress","ThreadId":1,"AppDomainId":2,"AppDomainAppId":"LMW3SVC2ROOT","MachineName":"WKWIN4480425","Log4NetLevel":"INFO ","HttpRequestNumber":1,"HttpRequestId":"90fe43c2-132e-45c4-97bc-490d8fec026c"}
{"@t":"2024-04-18T11:16:27.4260101Z","@mt":"{StartMessage} [Timing {TimingId}]","StartMessage":"Loading content from local cache file","TimingId":"7227daa","SourceContext":"Umbraco.Web.PublishedCache.NuCache.PublishedSnapshotService","ProcessId":7208,"ProcessName":"iisexpress","ThreadId":1,"AppDomainId":2,"AppDomainAppId":"LMW3SVC2ROOT","MachineName":"WKWIN4480425","Log4NetLevel":"INFO ","HttpRequestNumber":1,"HttpRequestId":"90fe43c2-132e-45c4-97bc-490d8fec026c"}
{"@t":"2024-04-18T11:16:28.6383829Z","@mt":"{EndMessage} ({Duration}ms) [Timing {TimingId}]","EndMessage":"Completed.","Duration":1211,"TimingId":"7227daa","SourceContext":"Umbraco.Web.PublishedCache.NuCache.PublishedSnapshotService","ProcessId":7208,"ProcessName":"iisexpress","ThreadId":1,"AppDomainId":2,"AppDomainAppId":"LMW3SVC2ROOT","MachineName":"WKWIN4480425","Log4NetLevel":"INFO ","HttpRequestNumber":1,"HttpRequestId":"90fe43c2-132e-45c4-97bc-490d8fec026c"}
{"@t":"2024-04-18T11:16:28.6623175Z","@mt":"{StartMessage} [Timing {TimingId}]","StartMessage":"Loading media from local cache file","TimingId":"121604b","SourceContext":"Umbraco.Web.PublishedCache.NuCache.PublishedSnapshotService","ProcessId":7208,"ProcessName":"iisexpress","ThreadId":1,"AppDomainId":2,"AppDomainAppId":"LMW3SVC2ROOT","MachineName":"WKWIN4480425","Log4NetLevel":"INFO ","HttpRequestNumber":1,"HttpRequestId":"90fe43c2-132e-45c4-97bc-490d8fec026c"}
{"@t":"2024-04-18T11:16:29.1340600Z","@mt":"{EndMessage} ({Duration}ms) [Timing {TimingId}]","EndMessage":"Completed.","Duration":472,"TimingId":"121604b","SourceContext":"Umbraco.Web.PublishedCache.NuCache.PublishedSnapshotService","ProcessId":7208,"ProcessName":"iisexpress","ThreadId":1,"AppDomainId":2,"AppDomainAppId":"LMW3SVC2ROOT","MachineName":"WKWIN4480425","Log4NetLevel":"INFO ","HttpRequestNumber":1,"HttpRequestId":"90fe43c2-132e-45c4-97bc-490d8fec026c"}
{"@t":"2024-04-18T11:16:29.7015430Z","@mt":"Initializing Umbraco internal event handlers for cache refreshing.","SourceContext":"Umbraco.Web.Cache.DistributedCacheBinderComponent","ProcessId":7208,"ProcessName":"iisexpress","ThreadId":1,"AppDomainId":2,"AppDomainAppId":"LMW3SVC2ROOT","MachineName":"WKWIN4480425","Log4NetLevel":"INFO ","HttpRequestNumber":1,"HttpRequestId":"90fe43c2-132e-45c4-97bc-490d8fec026c"}
{"@t":"2024-04-18T11:16:29.8860501Z","@mt":"Adding examine event handlers for {RegisteredIndexers} index providers.","RegisteredIndexers":3,"SourceContext":"Umbraco.Web.Search.ExamineComponent","ProcessId":7208,"ProcessName":"iisexpress","ThreadId":1,"AppDomainId":2,"AppDomainAppId":"LMW3SVC2ROOT","MachineName":"WKWIN4480425","Log4NetLevel":"INFO ","HttpRequestNumber":1,"HttpRequestId":"90fe43c2-132e-45c4-97bc-490d8fec026c"}
{"@t":"2024-04-18T11:16:37.0287104Z","@mt":"Starting '{MigrationName}'...","MigrationName":"Skybrud.Umbraco.Redirects","SourceContext":"Umbraco.Core.Migrations.MigrationPlan","ProcessId":7208,"ProcessName":"iisexpress","ThreadId":1,"AppDomainId":2,"AppDomainAppId":"LMW3SVC2ROOT","MachineName":"WKWIN4480425","Log4NetLevel":"INFO ","HttpRequestNumber":1,"HttpRequestId":"90fe43c2-132e-45c4-97bc-490d8fec026c"}
{"@t":"2024-04-18T11:16:37.0287104Z","@mt":"At {OrigState}","OrigState":"2.1.1","SourceContext":"Umbraco.Core.Migrations.MigrationPlan","ProcessId":7208,"ProcessName":"iisexpress","ThreadId":1,"AppDomainId":2,"AppDomainAppId":"LMW3SVC2ROOT","MachineName":"WKWIN4480425","Log4NetLevel":"INFO ","HttpRequestNumber":1,"HttpRequestId":"90fe43c2-132e-45c4-97bc-490d8fec026c"}
{"@t":"2024-04-18T11:16:37.0297077Z","@mt":"Done (pending scope completion).","SourceContext":"Umbraco.Core.Migrations.MigrationPlan","ProcessId":7208,"ProcessName":"iisexpress","ThreadId":1,"AppDomainId":2,"AppDomainAppId":"LMW3SVC2ROOT","MachineName":"WKWIN4480425","Log4NetLevel":"INFO ","HttpRequestNumber":1,"HttpRequestId":"90fe43c2-132e-45c4-97bc-490d8fec026c"}
{"@t":"2024-04-18T11:16:37.0376872Z","@mt":"Starting initialize async background thread.","SourceContext":"Umbraco.Web.Search.BackgroundIndexRebuilder","ProcessId":7208,"ProcessName":"iisexpress","ThreadId":1,"AppDomainId":2,"AppDomainAppId":"LMW3SVC2ROOT","MachineName":"WKWIN4480425","Log4NetLevel":"INFO ","HttpRequestNumber":1,"HttpRequestId":"90fe43c2-132e-45c4-97bc-490d8fec026c"}
{"@t":"2024-04-18T11:16:37.0406796Z","@mt":"{EndMessage} ({Duration}ms) [Timing {TimingId}]","EndMessage":"Booted.","Duration":14189,"TimingId":"3966b3c","SourceContext":"Umbraco.Core.Runtime.CoreRuntime","ProcessId":7208,"ProcessName":"iisexpress","ThreadId":1,"AppDomainId":2,"AppDomainAppId":"LMW3SVC2ROOT","MachineName":"WKWIN4480425","Log4NetLevel":"INFO ","HttpRequestNumber":1,"HttpRequestId":"90fe43c2-132e-45c4-97bc-490d8fec026c"}
{"@t":"2024-04-18T11:16:37.5617615Z","@mt":"New url {Url} detected, re-discovering application url.","Url":"http://localhost/umbraco","SourceContext":"Umbraco.Core.Sync.ApplicationUrlHelper","ProcessId":7208,"ProcessName":"iisexpress","ThreadId":6,"AppDomainId":2,"AppDomainAppId":"LMW3SVC2ROOT","MachineName":"WKWIN4480425","Log4NetLevel":"INFO ","HttpRequestNumber":2,"HttpRequestId":"cc7c7724-4038-4046-953e-cf923b9925b7"}
{"@t":"2024-04-18T11:16:37.5637544Z","@mt":"ApplicationUrl: {UmbracoAppUrl} (UmbracoModule request)","UmbracoAppUrl":"http://localhost/umbraco","SourceContext":"Umbraco.Core.Sync.ApplicationUrlHelper","ProcessId":7208,"ProcessName":"iisexpress","ThreadId":6,"AppDomainId":2,"AppDomainAppId":"LMW3SVC2ROOT","MachineName":"WKWIN4480425","Log4NetLevel":"INFO ","HttpRequestNumber":2,"HttpRequestId":"cc7c7724-4038-4046-953e-cf923b9925b7"}
{"@t":"2024-04-18T11:16:39.2890919Z","@mt":"The current Document Type {ContentTypeAlias} matches a locally declared controller of type {ControllerName}. Custom Controllers for Umbraco routing must implement '{UmbracoRenderController}' and inherit from '{UmbracoControllerBase}'.","@l":"Warning","ContentTypeAlias":"home","ControllerName":"HPPlc.Controllers.HomeController","UmbracoRenderController":"Umbraco.Web.Mvc.IRenderController","UmbracoControllerBase":"System.Web.Mvc.ControllerBase","SourceContext":"Umbraco.Web.Mvc.RenderRouteHandler","ProcessId":7208,"ProcessName":"iisexpress","ThreadId":6,"AppDomainId":2,"AppDomainAppId":"LMW3SVC2ROOT","MachineName":"WKWIN4480425","Log4NetLevel":"WARN ","HttpRequestNumber":2,"HttpRequestId":"cc7c7724-4038-4046-953e-cf923b9925b7"}
{"@t":"2024-04-18T11:19:39.6818400Z","@mt":"Scheduled health check results:","SourceContext":"Umbraco.Web.HealthCheck.HealthCheckResults","ProcessId":7208,"ProcessName":"iisexpress","ThreadId":6,"AppDomainId":2,"AppDomainAppId":"LMW3SVC2ROOT","MachineName":"WKWIN4480425","Log4NetLevel":"INFO "}
{"@t":"2024-04-18T11:19:39.6818400Z","@mt":"Checks for '{HealthCheckName}' all completed successfully.","HealthCheckName":"Folder & File Permissions","SourceContext":"Umbraco.Web.HealthCheck.HealthCheckResults","ProcessId":7208,"ProcessName":"iisexpress","ThreadId":6,"AppDomainId":2,"AppDomainAppId":"LMW3SVC2ROOT","MachineName":"WKWIN4480425","Log4NetLevel":"INFO "}
{"@t":"2024-04-18T11:19:39.6818400Z","@mt":"Result for {HealthCheckName}: {HealthCheckResult}, Message: '{HealthCheckMessage}'","HealthCheckName":"Folder & File Permissions","HealthCheckResult":"Success","HealthCheckMessage":"All folders have the correct permissions set.","SourceContext":"Umbraco.Web.HealthCheck.HealthCheckResults","ProcessId":7208,"ProcessName":"iisexpress","ThreadId":6,"AppDomainId":2,"AppDomainAppId":"LMW3SVC2ROOT","MachineName":"WKWIN4480425","Log4NetLevel":"INFO "}
{"@t":"2024-04-18T11:19:39.6818400Z","@mt":"Result for {HealthCheckName}: {HealthCheckResult}, Message: '{HealthCheckMessage}'","HealthCheckName":"Folder & File Permissions","HealthCheckResult":"Success","HealthCheckMessage":"All files have the correct permissions set.","SourceContext":"Umbraco.Web.HealthCheck.HealthCheckResults","ProcessId":7208,"ProcessName":"iisexpress","ThreadId":6,"AppDomainId":2,"AppDomainAppId":"LMW3SVC2ROOT","MachineName":"WKWIN4480425","Log4NetLevel":"INFO "}
{"@t":"2024-04-18T11:19:39.6818400Z","@mt":"Checks for '{HealthCheckName}' completed with errors.","@l":"Warning","HealthCheckName":"SMTP Settings","SourceContext":"Umbraco.Web.HealthCheck.HealthCheckResults","ProcessId":7208,"ProcessName":"iisexpress","ThreadId":6,"AppDomainId":2,"AppDomainAppId":"LMW3SVC2ROOT","MachineName":"WKWIN4480425","Log4NetLevel":"WARN "}
{"@t":"2024-04-18T11:19:39.6818400Z","@mt":"Result for {HealthCheckName}: {HealthCheckResult}, Message: '{HealthCheckMessage}'","HealthCheckName":"SMTP Settings","HealthCheckResult":"Error","HealthCheckMessage":"In the Web.config file system.net/mailsettings section, the host is not configured.","SourceContext":"Umbraco.Web.HealthCheck.HealthCheckResults","ProcessId":7208,"ProcessName":"iisexpress","ThreadId":6,"AppDomainId":2,"AppDomainAppId":"LMW3SVC2ROOT","MachineName":"WKWIN4480425","Log4NetLevel":"INFO "}
{"@t":"2024-04-18T11:19:39.6818400Z","@mt":"Checks for '{HealthCheckName}' completed with errors.","@l":"Warning","HealthCheckName":"Macro errors","SourceContext":"Umbraco.Web.HealthCheck.HealthCheckResults","ProcessId":7208,"ProcessName":"iisexpress","ThreadId":6,"AppDomainId":2,"AppDomainAppId":"LMW3SVC2ROOT","MachineName":"WKWIN4480425","Log4NetLevel":"WARN "}
{"@t":"2024-04-18T11:19:39.6818400Z","@mt":"Result for {HealthCheckName}: {HealthCheckResult}, Message: '{HealthCheckMessage}'","HealthCheckName":"Macro errors","HealthCheckResult":"Error","HealthCheckMessage":"MacroErrors are set to 'throw' which will prevent some or all pages in your site from loading completely if there are any errors in macros. Rectifying this will set the value to 'inline'.","SourceContext":"Umbraco.Web.HealthCheck.HealthCheckResults","ProcessId":7208,"ProcessName":"iisexpress","ThreadId":6,"AppDomainId":2,"AppDomainAppId":"LMW3SVC2ROOT","MachineName":"WKWIN4480425","Log4NetLevel":"INFO "}
{"@t":"2024-04-18T11:19:39.6818400Z","@mt":"Checks for '{HealthCheckName}' completed with errors.","@l":"Warning","HealthCheckName":"Notification Email Settings","SourceContext":"Umbraco.Web.HealthCheck.HealthCheckResults","ProcessId":7208,"ProcessName":"iisexpress","ThreadId":6,"AppDomainId":2,"AppDomainAppId":"LMW3SVC2ROOT","MachineName":"WKWIN4480425","Log4NetLevel":"WARN "}
{"@t":"2024-04-18T11:19:39.6818400Z","@mt":"Result for {HealthCheckName}: {HealthCheckResult}, Message: '{HealthCheckMessage}'","HealthCheckName":"Notification Email Settings","HealthCheckResult":"Error","HealthCheckMessage":"Notification email is still set to the default value of <strong>your@email.here</strong>.","SourceContext":"Umbraco.Web.HealthCheck.HealthCheckResults","ProcessId":7208,"ProcessName":"iisexpress","ThreadId":6,"AppDomainId":2,"AppDomainAppId":"LMW3SVC2ROOT","MachineName":"WKWIN4480425","Log4NetLevel":"INFO "}
{"@t":"2024-04-18T11:19:39.6818400Z","@mt":"Checks for '{HealthCheckName}' all completed successfully.","HealthCheckName":"Try Skip IIS Custom Errors","SourceContext":"Umbraco.Web.HealthCheck.HealthCheckResults","ProcessId":7208,"ProcessName":"iisexpress","ThreadId":6,"AppDomainId":2,"AppDomainAppId":"LMW3SVC2ROOT","MachineName":"WKWIN4480425","Log4NetLevel":"INFO "}
{"@t":"2024-04-18T11:19:39.6818400Z","@mt":"Result for {HealthCheckName}: {HealthCheckResult}, Message: '{HealthCheckMessage}'","HealthCheckName":"Try Skip IIS Custom Errors","HealthCheckResult":"Success","HealthCheckMessage":"Try Skip IIS Custom Errors is set to 'true' and you're using IIS version '10.0'.","SourceContext":"Umbraco.Web.HealthCheck.HealthCheckResults","ProcessId":7208,"ProcessName":"iisexpress","ThreadId":6,"AppDomainId":2,"AppDomainAppId":"LMW3SVC2ROOT","MachineName":"WKWIN4480425","Log4NetLevel":"INFO "}
{"@t":"2024-04-18T11:19:39.6818400Z","@mt":"Checks for '{HealthCheckName}' completed with errors.","@l":"Warning","HealthCheckName":"Custom Errors","SourceContext":"Umbraco.Web.HealthCheck.HealthCheckResults","ProcessId":7208,"ProcessName":"iisexpress","ThreadId":6,"AppDomainId":2,"AppDomainAppId":"LMW3SVC2ROOT","MachineName":"WKWIN4480425","Log4NetLevel":"WARN "}
{"@t":"2024-04-18T11:19:39.6818400Z","@mt":"Result for {HealthCheckName}: {HealthCheckResult}, Message: '{HealthCheckMessage}'","HealthCheckName":"Custom Errors","HealthCheckResult":"Error","HealthCheckMessage":"Unable to find <strong>'/configuration/system.web/customErrors/@mode'</strong> in config file <strong>'C:\\Projects\\HP Proj\\HP PLC\\Preprod\\HPPlc_PreProd_Index_BW_Live\\HPPlc\\Web.config'</strong>.","SourceContext":"Umbraco.Web.HealthCheck.HealthCheckResults","ProcessId":7208,"ProcessName":"iisexpress","ThreadId":6,"AppDomainId":2,"AppDomainAppId":"LMW3SVC2ROOT","MachineName":"WKWIN4480425","Log4NetLevel":"INFO "}
{"@t":"2024-04-18T11:19:39.6818400Z","@mt":"Checks for '{HealthCheckName}' all completed successfully.","HealthCheckName":"Trace Mode","SourceContext":"Umbraco.Web.HealthCheck.HealthCheckResults","ProcessId":7208,"ProcessName":"iisexpress","ThreadId":6,"AppDomainId":2,"AppDomainAppId":"LMW3SVC2ROOT","MachineName":"WKWIN4480425","Log4NetLevel":"INFO "}
{"@t":"2024-04-18T11:19:39.6818400Z","@mt":"Result for {HealthCheckName}: {HealthCheckResult}, Message: '{HealthCheckMessage}'","HealthCheckName":"Trace Mode","HealthCheckResult":"Success","HealthCheckMessage":"Trace mode is disabled.","SourceContext":"Umbraco.Web.HealthCheck.HealthCheckResults","ProcessId":7208,"ProcessName":"iisexpress","ThreadId":6,"AppDomainId":2,"AppDomainAppId":"LMW3SVC2ROOT","MachineName":"WKWIN4480425","Log4NetLevel":"INFO "}
{"@t":"2024-04-18T11:19:39.6818400Z","@mt":"Checks for '{HealthCheckName}' completed with errors.","@l":"Warning","HealthCheckName":"Debug Compilation Mode","SourceContext":"Umbraco.Web.HealthCheck.HealthCheckResults","ProcessId":7208,"ProcessName":"iisexpress","ThreadId":6,"AppDomainId":2,"AppDomainAppId":"LMW3SVC2ROOT","MachineName":"WKWIN4480425","Log4NetLevel":"WARN "}
{"@t":"2024-04-18T11:19:39.6818400Z","@mt":"Result for {HealthCheckName}: {HealthCheckResult}, Message: '{HealthCheckMessage}'","HealthCheckName":"Debug Compilation Mode","HealthCheckResult":"Error","HealthCheckMessage":"Debug compilation mode is currently enabled. It is recommended to disable this setting before go live.","SourceContext":"Umbraco.Web.HealthCheck.HealthCheckResults","ProcessId":7208,"ProcessName":"iisexpress","ThreadId":6,"AppDomainId":2,"AppDomainAppId":"LMW3SVC2ROOT","MachineName":"WKWIN4480425","Log4NetLevel":"INFO "}
{"@t":"2024-04-18T11:19:39.6818400Z","@mt":"Checks for '{HealthCheckName}' completed with errors.","@l":"Warning","HealthCheckName":"Cross-site scripting Protection (X-XSS-Protection header)","SourceContext":"Umbraco.Web.HealthCheck.HealthCheckResults","ProcessId":7208,"ProcessName":"iisexpress","ThreadId":6,"AppDomainId":2,"AppDomainAppId":"LMW3SVC2ROOT","MachineName":"WKWIN4480425","Log4NetLevel":"WARN "}
{"@t":"2024-04-18T11:19:39.6818400Z","@mt":"Result for {HealthCheckName}: {HealthCheckResult}, Message: '{HealthCheckMessage}'","HealthCheckName":"Cross-site scripting Protection (X-XSS-Protection header)","HealthCheckResult":"Error","HealthCheckMessage":"Error pinging the URL http://localhost/umbraco - 'The remote server returned an error: (404) Not Found.'","SourceContext":"Umbraco.Web.HealthCheck.HealthCheckResults","ProcessId":7208,"ProcessName":"iisexpress","ThreadId":6,"AppDomainId":2,"AppDomainAppId":"LMW3SVC2ROOT","MachineName":"WKWIN4480425","Log4NetLevel":"INFO "}
{"@t":"2024-04-18T11:19:39.6818400Z","@mt":"Checks for '{HealthCheckName}' completed with errors.","@l":"Warning","HealthCheckName":"Cookie hijacking and protocol downgrade attacks Protection (Strict-Transport-Security Header (HSTS))","SourceContext":"Umbraco.Web.HealthCheck.HealthCheckResults","ProcessId":7208,"ProcessName":"iisexpress","ThreadId":6,"AppDomainId":2,"AppDomainAppId":"LMW3SVC2ROOT","MachineName":"WKWIN4480425","Log4NetLevel":"WARN "}
{"@t":"2024-04-18T11:19:39.6818400Z","@mt":"Result for {HealthCheckName}: {HealthCheckResult}, Message: '{HealthCheckMessage}'","HealthCheckName":"Cookie hijacking and protocol downgrade attacks Protection (Strict-Transport-Security Header (HSTS))","HealthCheckResult":"Error","HealthCheckMessage":"Error pinging the URL http://localhost/umbraco - 'The remote server returned an error: (404) Not Found.'","SourceContext":"Umbraco.Web.HealthCheck.HealthCheckResults","ProcessId":7208,"ProcessName":"iisexpress","ThreadId":6,"AppDomainId":2,"AppDomainAppId":"LMW3SVC2ROOT","MachineName":"WKWIN4480425","Log4NetLevel":"INFO "}
{"@t":"2024-04-18T11:19:39.6818400Z","@mt":"Checks for '{HealthCheckName}' completed with errors.","@l":"Warning","HealthCheckName":"Content/MIME Sniffing Protection","SourceContext":"Umbraco.Web.HealthCheck.HealthCheckResults","ProcessId":7208,"ProcessName":"iisexpress","ThreadId":6,"AppDomainId":2,"AppDomainAppId":"LMW3SVC2ROOT","MachineName":"WKWIN4480425","Log4NetLevel":"WARN "}
{"@t":"2024-04-18T11:19:39.6818400Z","@mt":"Result for {HealthCheckName}: {HealthCheckResult}, Message: '{HealthCheckMessage}'","HealthCheckName":"Content/MIME Sniffing Protection","HealthCheckResult":"Error","HealthCheckMessage":"Error pinging the URL http://localhost/umbraco - 'The remote server returned an error: (404) Not Found.'","SourceContext":"Umbraco.Web.HealthCheck.HealthCheckResults","ProcessId":7208,"ProcessName":"iisexpress","ThreadId":6,"AppDomainId":2,"AppDomainAppId":"LMW3SVC2ROOT","MachineName":"WKWIN4480425","Log4NetLevel":"INFO "}
{"@t":"2024-04-18T11:19:39.6818400Z","@mt":"Checks for '{HealthCheckName}' completed with errors.","@l":"Warning","HealthCheckName":"Excessive Headers","SourceContext":"Umbraco.Web.HealthCheck.HealthCheckResults","ProcessId":7208,"ProcessName":"iisexpress","ThreadId":6,"AppDomainId":2,"AppDomainAppId":"LMW3SVC2ROOT","MachineName":"WKWIN4480425","Log4NetLevel":"WARN "}
{"@t":"2024-04-18T11:19:39.6818400Z","@mt":"Result for {HealthCheckName}: {HealthCheckResult}, Message: '{HealthCheckMessage}'","HealthCheckName":"Excessive Headers","HealthCheckResult":"Warning","HealthCheckMessage":"[httpsCheckInvalidUrl]","SourceContext":"Umbraco.Web.HealthCheck.HealthCheckResults","ProcessId":7208,"ProcessName":"iisexpress","ThreadId":6,"AppDomainId":2,"AppDomainAppId":"LMW3SVC2ROOT","MachineName":"WKWIN4480425","Log4NetLevel":"INFO "}
{"@t":"2024-04-18T11:19:39.6818400Z","@mt":"Checks for '{HealthCheckName}' completed with errors.","@l":"Warning","HealthCheckName":"Click-Jacking Protection","SourceContext":"Umbraco.Web.HealthCheck.HealthCheckResults","ProcessId":7208,"ProcessName":"iisexpress","ThreadId":6,"AppDomainId":2,"AppDomainAppId":"LMW3SVC2ROOT","MachineName":"WKWIN4480425","Log4NetLevel":"WARN "}
{"@t":"2024-04-18T11:19:39.6818400Z","@mt":"Result for {HealthCheckName}: {HealthCheckResult}, Message: '{HealthCheckMessage}'","HealthCheckName":"Click-Jacking Protection","HealthCheckResult":"Error","HealthCheckMessage":"Error pinging the URL http://localhost/umbraco - 'The remote server returned an error: (404) Not Found.'","SourceContext":"Umbraco.Web.HealthCheck.HealthCheckResults","ProcessId":7208,"ProcessName":"iisexpress","ThreadId":6,"AppDomainId":2,"AppDomainAppId":"LMW3SVC2ROOT","MachineName":"WKWIN4480425","Log4NetLevel":"INFO "}
{"@t":"2024-04-18T11:19:39.6818400Z","@mt":"Checks for '{HealthCheckName}' completed with errors.","@l":"Warning","HealthCheckName":"HTTPS Configuration","SourceContext":"Umbraco.Web.HealthCheck.HealthCheckResults","ProcessId":7208,"ProcessName":"iisexpress","ThreadId":6,"AppDomainId":2,"AppDomainAppId":"LMW3SVC2ROOT","MachineName":"WKWIN4480425","Log4NetLevel":"WARN "}
{"@t":"2024-04-18T11:19:39.6818400Z","@mt":"Result for {HealthCheckName}: {HealthCheckResult}, Message: '{HealthCheckMessage}'","HealthCheckName":"HTTPS Configuration","HealthCheckResult":"Error","HealthCheckMessage":"You are currently not viewing the site using the HTTPS scheme.","SourceContext":"Umbraco.Web.HealthCheck.HealthCheckResults","ProcessId":7208,"ProcessName":"iisexpress","ThreadId":6,"AppDomainId":2,"AppDomainAppId":"LMW3SVC2ROOT","MachineName":"WKWIN4480425","Log4NetLevel":"INFO "}
{"@t":"2024-04-18T11:19:39.6818400Z","@mt":"Result for {HealthCheckName}: {HealthCheckResult}, Message: '{HealthCheckMessage}'","HealthCheckName":"HTTPS Configuration","HealthCheckResult":"Info","HealthCheckMessage":"The appSetting 'Umbraco.Core.UseHttps' is set to 'false' in your web.config file. Once you access this site using the HTTPS scheme, that should be set to 'true'.","SourceContext":"Umbraco.Web.HealthCheck.HealthCheckResults","ProcessId":7208,"ProcessName":"iisexpress","ThreadId":6,"AppDomainId":2,"AppDomainAppId":"LMW3SVC2ROOT","MachineName":"WKWIN4480425","Log4NetLevel":"INFO "}
{"@t":"2024-04-18T11:19:39.6818400Z","@mt":"Result for {HealthCheckName}: {HealthCheckResult}, Message: '{HealthCheckMessage}'","HealthCheckName":"HTTPS Configuration","HealthCheckResult":"Error","HealthCheckMessage":"Error pinging the URL https://localhost/umbraco - 'The underlying connection was closed: An unexpected error occurred on a send.'","SourceContext":"Umbraco.Web.HealthCheck.HealthCheckResults","ProcessId":7208,"ProcessName":"iisexpress","ThreadId":6,"AppDomainId":2,"AppDomainAppId":"LMW3SVC2ROOT","MachineName":"WKWIN4480425","Log4NetLevel":"INFO "}
{"@t":"2024-04-18T11:19:39.6818400Z","@mt":"Checks for '{HealthCheckName}' all completed successfully.","HealthCheckName":"Database data integrity check","SourceContext":"Umbraco.Web.HealthCheck.HealthCheckResults","ProcessId":7208,"ProcessName":"iisexpress","ThreadId":6,"AppDomainId":2,"AppDomainAppId":"LMW3SVC2ROOT","MachineName":"WKWIN4480425","Log4NetLevel":"INFO "}
{"@t":"2024-04-18T11:19:39.6818400Z","@mt":"Result for {HealthCheckName}: {HealthCheckResult}, Message: '{HealthCheckMessage}'","HealthCheckName":"Database data integrity check","HealthCheckResult":"Success","HealthCheckMessage":"<p>All document paths are valid</p>\r\n","SourceContext":"Umbraco.Web.HealthCheck.HealthCheckResults","ProcessId":7208,"ProcessName":"iisexpress","ThreadId":6,"AppDomainId":2,"AppDomainAppId":"LMW3SVC2ROOT","MachineName":"WKWIN4480425","Log4NetLevel":"INFO "}
{"@t":"2024-04-18T11:19:39.6818400Z","@mt":"Result for {HealthCheckName}: {HealthCheckResult}, Message: '{HealthCheckMessage}'","HealthCheckName":"Database data integrity check","HealthCheckResult":"Success","HealthCheckMessage":"<p>All media paths are valid</p>\r\n","SourceContext":"Umbraco.Web.HealthCheck.HealthCheckResults","ProcessId":7208,"ProcessName":"iisexpress","ThreadId":6,"AppDomainId":2,"AppDomainAppId":"LMW3SVC2ROOT","MachineName":"WKWIN4480425","Log4NetLevel":"INFO "}
{"@t":"2024-04-18T11:21:50.0306613Z","@mt":"{StartMessage} [Timing {TimingId}]","StartMessage":"Booting Umbraco 8.12.2.","TimingId":"075a483","SourceContext":"Umbraco.Core.Runtime.CoreRuntime","ProcessId":32244,"ProcessName":"iisexpress","ThreadId":1,"AppDomainId":2,"AppDomainAppId":"LMW3SVC2ROOT","MachineName":"WKWIN4480425","Log4NetLevel":"INFO ","HttpRequestNumber":1,"HttpRequestId":"45cb0d4e-cba7-485c-851f-da74b75b75f9"}
{"@t":"2024-04-18T11:21:50.0585864Z","@mt":"Booting site '{HostingSiteName}', app '{HostingApplicationID}', path '{HostingPhysicalPath}', server '{MachineName}'.","HostingSiteName":"HPPlc","HostingApplicationID":"/LM/W3SVC/2/ROOT","HostingPhysicalPath":"C:\\Projects\\HP Proj\\HP PLC\\Preprod\\HPPlc_PreProd_Index_BW_Live\\HPPlc\\","MachineName":"WKWIN4480425","SourceContext":"Umbraco.Core.Runtime.CoreRuntime","ProcessId":32244,"ProcessName":"iisexpress","ThreadId":1,"AppDomainId":2,"AppDomainAppId":"LMW3SVC2ROOT","Log4NetLevel":"INFO ","HttpRequestNumber":1,"HttpRequestId":"45cb0d4e-cba7-485c-851f-da74b75b75f9"}
{"@t":"2024-04-18T11:21:50.1942257Z","@mt":"Acquiring.","SourceContext":"Umbraco.Core.Runtime.MainDom","ProcessId":32244,"ProcessName":"iisexpress","ThreadId":1,"AppDomainId":2,"AppDomainAppId":"LMW3SVC2ROOT","MachineName":"WKWIN4480425","Log4NetLevel":"INFO ","HttpRequestNumber":1,"HttpRequestId":"45cb0d4e-cba7-485c-851f-da74b75b75f9"}
{"@t":"2024-04-18T11:21:50.1952231Z","@mt":"Acquired.","SourceContext":"Umbraco.Core.Runtime.MainDom","ProcessId":32244,"ProcessName":"iisexpress","ThreadId":1,"AppDomainId":2,"AppDomainAppId":"LMW3SVC2ROOT","MachineName":"WKWIN4480425","Log4NetLevel":"INFO ","HttpRequestNumber":1,"HttpRequestId":"45cb0d4e-cba7-485c-851f-da74b75b75f9"}
{"@t":"2024-04-18T11:21:51.7070795Z","@mt":"{StartMessage} [Timing {TimingId}]","StartMessage":"Resolving composer types.","TimingId":"570942b","SourceContext":"Umbraco.Core.Runtime.CoreRuntime","ProcessId":32244,"ProcessName":"iisexpress","ThreadId":1,"AppDomainId":2,"AppDomainAppId":"LMW3SVC2ROOT","MachineName":"WKWIN4480425","Log4NetLevel":"INFO ","HttpRequestNumber":1,"HttpRequestId":"45cb0d4e-cba7-485c-851f-da74b75b75f9"}
{"@t":"2024-04-18T11:21:51.9509880Z","@mt":"{EndMessage} ({Duration}ms) [Timing {TimingId}]","EndMessage":"Resolved.","Duration":243,"TimingId":"570942b","SourceContext":"Umbraco.Core.Runtime.CoreRuntime","ProcessId":32244,"ProcessName":"iisexpress","ThreadId":1,"AppDomainId":2,"AppDomainAppId":"LMW3SVC2ROOT","MachineName":"WKWIN4480425","Log4NetLevel":"INFO ","HttpRequestNumber":1,"HttpRequestId":"45cb0d4e-cba7-485c-851f-da74b75b75f9"}
{"@t":"2024-04-18T11:21:52.7722839Z","@mt":"Registered with MainDom, localContentDbExists? {LocalContentDbExists}, localMediaDbExists? {LocalMediaDbExists}","LocalContentDbExists":true,"LocalMediaDbExists":true,"SourceContext":"Umbraco.Web.PublishedCache.NuCache.PublishedSnapshotService","ProcessId":32244,"ProcessName":"iisexpress","ThreadId":1,"AppDomainId":2,"AppDomainAppId":"LMW3SVC2ROOT","MachineName":"WKWIN4480425","Log4NetLevel":"INFO ","HttpRequestNumber":1,"HttpRequestId":"45cb0d4e-cba7-485c-851f-da74b75b75f9"}
{"@t":"2024-04-18T11:21:52.7722839Z","@mt":"Creating the content store, localContentDbExists? {LocalContentDbExists}","LocalContentDbExists":true,"SourceContext":"Umbraco.Web.PublishedCache.NuCache.PublishedSnapshotService","ProcessId":32244,"ProcessName":"iisexpress","ThreadId":1,"AppDomainId":2,"AppDomainAppId":"LMW3SVC2ROOT","MachineName":"WKWIN4480425","Log4NetLevel":"INFO ","HttpRequestNumber":1,"HttpRequestId":"45cb0d4e-cba7-485c-851f-da74b75b75f9"}
{"@t":"2024-04-18T11:21:52.7732791Z","@mt":"Creating the media store, localMediaDbExists? {LocalMediaDbExists}","LocalMediaDbExists":true,"SourceContext":"Umbraco.Web.PublishedCache.NuCache.PublishedSnapshotService","ProcessId":32244,"ProcessName":"iisexpress","ThreadId":1,"AppDomainId":2,"AppDomainAppId":"LMW3SVC2ROOT","MachineName":"WKWIN4480425","Log4NetLevel":"INFO ","HttpRequestNumber":1,"HttpRequestId":"45cb0d4e-cba7-485c-851f-da74b75b75f9"}
{"@t":"2024-04-18T11:21:53.2727085Z","@mt":"{StartMessage} [Timing {TimingId}]","StartMessage":"Loading content from local cache file","TimingId":"a435c8f","SourceContext":"Umbraco.Web.PublishedCache.NuCache.PublishedSnapshotService","ProcessId":32244,"ProcessName":"iisexpress","ThreadId":1,"AppDomainId":2,"AppDomainAppId":"LMW3SVC2ROOT","MachineName":"WKWIN4480425","Log4NetLevel":"INFO ","HttpRequestNumber":1,"HttpRequestId":"45cb0d4e-cba7-485c-851f-da74b75b75f9"}
{"@t":"2024-04-18T11:21:53.9578830Z","@mt":"{EndMessage} ({Duration}ms) [Timing {TimingId}]","EndMessage":"Completed.","Duration":685,"TimingId":"a435c8f","SourceContext":"Umbraco.Web.PublishedCache.NuCache.PublishedSnapshotService","ProcessId":32244,"ProcessName":"iisexpress","ThreadId":1,"AppDomainId":2,"AppDomainAppId":"LMW3SVC2ROOT","MachineName":"WKWIN4480425","Log4NetLevel":"INFO ","HttpRequestNumber":1,"HttpRequestId":"45cb0d4e-cba7-485c-851f-da74b75b75f9"}
{"@t":"2024-04-18T11:21:53.9758353Z","@mt":"{StartMessage} [Timing {TimingId}]","StartMessage":"Loading media from local cache file","TimingId":"63dc738","SourceContext":"Umbraco.Web.PublishedCache.NuCache.PublishedSnapshotService","ProcessId":32244,"ProcessName":"iisexpress","ThreadId":1,"AppDomainId":2,"AppDomainAppId":"LMW3SVC2ROOT","MachineName":"WKWIN4480425","Log4NetLevel":"INFO ","HttpRequestNumber":1,"HttpRequestId":"45cb0d4e-cba7-485c-851f-da74b75b75f9"}
{"@t":"2024-04-18T11:21:54.3308906Z","@mt":"{EndMessage} ({Duration}ms) [Timing {TimingId}]","EndMessage":"Completed.","Duration":354,"TimingId":"63dc738","SourceContext":"Umbraco.Web.PublishedCache.NuCache.PublishedSnapshotService","ProcessId":32244,"ProcessName":"iisexpress","ThreadId":1,"AppDomainId":2,"AppDomainAppId":"LMW3SVC2ROOT","MachineName":"WKWIN4480425","Log4NetLevel":"INFO ","HttpRequestNumber":1,"HttpRequestId":"45cb0d4e-cba7-485c-851f-da74b75b75f9"}
{"@t":"2024-04-18T11:21:54.7142079Z","@mt":"Initializing Umbraco internal event handlers for cache refreshing.","SourceContext":"Umbraco.Web.Cache.DistributedCacheBinderComponent","ProcessId":32244,"ProcessName":"iisexpress","ThreadId":1,"AppDomainId":2,"AppDomainAppId":"LMW3SVC2ROOT","MachineName":"WKWIN4480425","Log4NetLevel":"INFO ","HttpRequestNumber":1,"HttpRequestId":"45cb0d4e-cba7-485c-851f-da74b75b75f9"}
{"@t":"2024-04-18T11:21:54.8299262Z","@mt":"Adding examine event handlers for {RegisteredIndexers} index providers.","RegisteredIndexers":3,"SourceContext":"Umbraco.Web.Search.ExamineComponent","ProcessId":32244,"ProcessName":"iisexpress","ThreadId":1,"AppDomainId":2,"AppDomainAppId":"LMW3SVC2ROOT","MachineName":"WKWIN4480425","Log4NetLevel":"INFO ","HttpRequestNumber":1,"HttpRequestId":"45cb0d4e-cba7-485c-851f-da74b75b75f9"}
{"@t":"2024-04-18T11:21:59.3945258Z","@mt":"Starting '{MigrationName}'...","MigrationName":"Skybrud.Umbraco.Redirects","SourceContext":"Umbraco.Core.Migrations.MigrationPlan","ProcessId":32244,"ProcessName":"iisexpress","ThreadId":1,"AppDomainId":2,"AppDomainAppId":"LMW3SVC2ROOT","MachineName":"WKWIN4480425","Log4NetLevel":"INFO ","HttpRequestNumber":1,"HttpRequestId":"45cb0d4e-cba7-485c-851f-da74b75b75f9"}
{"@t":"2024-04-18T11:21:59.3945258Z","@mt":"At {OrigState}","OrigState":"2.1.1","SourceContext":"Umbraco.Core.Migrations.MigrationPlan","ProcessId":32244,"ProcessName":"iisexpress","ThreadId":1,"AppDomainId":2,"AppDomainAppId":"LMW3SVC2ROOT","MachineName":"WKWIN4480425","Log4NetLevel":"INFO ","HttpRequestNumber":1,"HttpRequestId":"45cb0d4e-cba7-485c-851f-da74b75b75f9"}
{"@t":"2024-04-18T11:21:59.3955230Z","@mt":"Done (pending scope completion).","SourceContext":"Umbraco.Core.Migrations.MigrationPlan","ProcessId":32244,"ProcessName":"iisexpress","ThreadId":1,"AppDomainId":2,"AppDomainAppId":"LMW3SVC2ROOT","MachineName":"WKWIN4480425","Log4NetLevel":"INFO ","HttpRequestNumber":1,"HttpRequestId":"45cb0d4e-cba7-485c-851f-da74b75b75f9"}
{"@t":"2024-04-18T11:21:59.4003765Z","@mt":"Starting initialize async background thread.","SourceContext":"Umbraco.Web.Search.BackgroundIndexRebuilder","ProcessId":32244,"ProcessName":"iisexpress","ThreadId":1,"AppDomainId":2,"AppDomainAppId":"LMW3SVC2ROOT","MachineName":"WKWIN4480425","Log4NetLevel":"INFO ","HttpRequestNumber":1,"HttpRequestId":"45cb0d4e-cba7-485c-851f-da74b75b75f9"}
{"@t":"2024-04-18T11:21:59.4043452Z","@mt":"{EndMessage} ({Duration}ms) [Timing {TimingId}]","EndMessage":"Booted.","Duration":9385,"TimingId":"075a483","SourceContext":"Umbraco.Core.Runtime.CoreRuntime","ProcessId":32244,"ProcessName":"iisexpress","ThreadId":1,"AppDomainId":2,"AppDomainAppId":"LMW3SVC2ROOT","MachineName":"WKWIN4480425","Log4NetLevel":"INFO ","HttpRequestNumber":1,"HttpRequestId":"45cb0d4e-cba7-485c-851f-da74b75b75f9"}
{"@t":"2024-04-18T11:21:59.7248945Z","@mt":"New url {Url} detected, re-discovering application url.","Url":"http://localhost/umbraco","SourceContext":"Umbraco.Core.Sync.ApplicationUrlHelper","ProcessId":32244,"ProcessName":"iisexpress","ThreadId":6,"AppDomainId":2,"AppDomainAppId":"LMW3SVC2ROOT","MachineName":"WKWIN4480425","Log4NetLevel":"INFO ","HttpRequestNumber":2,"HttpRequestId":"0781c669-b633-4cf3-a8d8-1f23d8e92d0e"}
{"@t":"2024-04-18T11:21:59.7270949Z","@mt":"ApplicationUrl: {UmbracoAppUrl} (UmbracoModule request)","UmbracoAppUrl":"http://localhost/umbraco","SourceContext":"Umbraco.Core.Sync.ApplicationUrlHelper","ProcessId":32244,"ProcessName":"iisexpress","ThreadId":6,"AppDomainId":2,"AppDomainAppId":"LMW3SVC2ROOT","MachineName":"WKWIN4480425","Log4NetLevel":"INFO ","HttpRequestNumber":2,"HttpRequestId":"0781c669-b633-4cf3-a8d8-1f23d8e92d0e"}
{"@t":"2024-04-18T11:22:01.0857320Z","@mt":"The current Document Type {ContentTypeAlias} matches a locally declared controller of type {ControllerName}. Custom Controllers for Umbraco routing must implement '{UmbracoRenderController}' and inherit from '{UmbracoControllerBase}'.","@l":"Warning","ContentTypeAlias":"home","ControllerName":"HPPlc.Controllers.HomeController","UmbracoRenderController":"Umbraco.Web.Mvc.IRenderController","UmbracoControllerBase":"System.Web.Mvc.ControllerBase","SourceContext":"Umbraco.Web.Mvc.RenderRouteHandler","ProcessId":32244,"ProcessName":"iisexpress","ThreadId":6,"AppDomainId":2,"AppDomainAppId":"LMW3SVC2ROOT","MachineName":"WKWIN4480425","Log4NetLevel":"WARN ","HttpRequestNumber":2,"HttpRequestId":"0781c669-b633-4cf3-a8d8-1f23d8e92d0e"}
{"@t":"2024-04-18T13:17:23.0395345Z","@mt":"{StartMessage} [Timing {TimingId}]","StartMessage":"Booting Umbraco 8.12.2.","TimingId":"20af180","SourceContext":"Umbraco.Core.Runtime.CoreRuntime","ProcessId":27972,"ProcessName":"iisexpress","ThreadId":1,"AppDomainId":2,"AppDomainAppId":"LMW3SVC2ROOT","MachineName":"WKWIN4480425","Log4NetLevel":"INFO ","HttpRequestNumber":1,"HttpRequestId":"38288a22-96cd-436b-8c54-7deacbc13276"}
{"@t":"2024-04-18T13:17:23.0884030Z","@mt":"Booting site '{HostingSiteName}', app '{HostingApplicationID}', path '{HostingPhysicalPath}', server '{MachineName}'.","HostingSiteName":"HPPlc","HostingApplicationID":"/LM/W3SVC/2/ROOT","HostingPhysicalPath":"C:\\Projects\\HP Proj\\HP PLC\\Preprod\\HPPlc_PreProd_Index_BW_Live\\HPPlc\\","MachineName":"WKWIN4480425","SourceContext":"Umbraco.Core.Runtime.CoreRuntime","ProcessId":27972,"ProcessName":"iisexpress","ThreadId":1,"AppDomainId":2,"AppDomainAppId":"LMW3SVC2ROOT","Log4NetLevel":"INFO ","HttpRequestNumber":1,"HttpRequestId":"38288a22-96cd-436b-8c54-7deacbc13276"}
{"@t":"2024-04-18T13:17:23.2305305Z","@mt":"Acquiring.","SourceContext":"Umbraco.Core.Runtime.MainDom","ProcessId":27972,"ProcessName":"iisexpress","ThreadId":1,"AppDomainId":2,"AppDomainAppId":"LMW3SVC2ROOT","MachineName":"WKWIN4480425","Log4NetLevel":"INFO ","HttpRequestNumber":1,"HttpRequestId":"38288a22-96cd-436b-8c54-7deacbc13276"}
{"@t":"2024-04-18T13:17:23.2335231Z","@mt":"Acquired.","SourceContext":"Umbraco.Core.Runtime.MainDom","ProcessId":27972,"ProcessName":"iisexpress","ThreadId":1,"AppDomainId":2,"AppDomainAppId":"LMW3SVC2ROOT","MachineName":"WKWIN4480425","Log4NetLevel":"INFO ","HttpRequestNumber":1,"HttpRequestId":"38288a22-96cd-436b-8c54-7deacbc13276"}
{"@t":"2024-04-18T13:17:25.6954375Z","@mt":"{StartMessage} [Timing {TimingId}]","StartMessage":"Resolving composer types.","TimingId":"2cab66b","SourceContext":"Umbraco.Core.Runtime.CoreRuntime","ProcessId":27972,"ProcessName":"iisexpress","ThreadId":1,"AppDomainId":2,"AppDomainAppId":"LMW3SVC2ROOT","MachineName":"WKWIN4480425","Log4NetLevel":"INFO ","HttpRequestNumber":1,"HttpRequestId":"38288a22-96cd-436b-8c54-7deacbc13276"}
{"@t":"2024-04-18T13:17:26.4205009Z","@mt":"{EndMessage} ({Duration}ms) [Timing {TimingId}]","EndMessage":"Resolved.","Duration":722,"TimingId":"2cab66b","SourceContext":"Umbraco.Core.Runtime.CoreRuntime","ProcessId":27972,"ProcessName":"iisexpress","ThreadId":1,"AppDomainId":2,"AppDomainAppId":"LMW3SVC2ROOT","MachineName":"WKWIN4480425","Log4NetLevel":"INFO ","HttpRequestNumber":1,"HttpRequestId":"38288a22-96cd-436b-8c54-7deacbc13276"}
{"@t":"2024-04-18T13:17:28.4095145Z","@mt":"Registered with MainDom, localContentDbExists? {LocalContentDbExists}, localMediaDbExists? {LocalMediaDbExists}","LocalContentDbExists":true,"LocalMediaDbExists":true,"SourceContext":"Umbraco.Web.PublishedCache.NuCache.PublishedSnapshotService","ProcessId":27972,"ProcessName":"iisexpress","ThreadId":1,"AppDomainId":2,"AppDomainAppId":"LMW3SVC2ROOT","MachineName":"WKWIN4480425","Log4NetLevel":"INFO ","HttpRequestNumber":1,"HttpRequestId":"38288a22-96cd-436b-8c54-7deacbc13276"}
{"@t":"2024-04-18T13:17:28.4095145Z","@mt":"Creating the content store, localContentDbExists? {LocalContentDbExists}","LocalContentDbExists":true,"SourceContext":"Umbraco.Web.PublishedCache.NuCache.PublishedSnapshotService","ProcessId":27972,"ProcessName":"iisexpress","ThreadId":1,"AppDomainId":2,"AppDomainAppId":"LMW3SVC2ROOT","MachineName":"WKWIN4480425","Log4NetLevel":"INFO ","HttpRequestNumber":1,"HttpRequestId":"38288a22-96cd-436b-8c54-7deacbc13276"}
{"@t":"2024-04-18T13:17:28.4135029Z","@mt":"Creating the media store, localMediaDbExists? {LocalMediaDbExists}","LocalMediaDbExists":true,"SourceContext":"Umbraco.Web.PublishedCache.NuCache.PublishedSnapshotService","ProcessId":27972,"ProcessName":"iisexpress","ThreadId":1,"AppDomainId":2,"AppDomainAppId":"LMW3SVC2ROOT","MachineName":"WKWIN4480425","Log4NetLevel":"INFO ","HttpRequestNumber":1,"HttpRequestId":"38288a22-96cd-436b-8c54-7deacbc13276"}
{"@t":"2024-04-18T13:17:29.6351632Z","@mt":"{StartMessage} [Timing {TimingId}]","StartMessage":"Loading content from local cache file","TimingId":"9507460","SourceContext":"Umbraco.Web.PublishedCache.NuCache.PublishedSnapshotService","ProcessId":27972,"ProcessName":"iisexpress","ThreadId":1,"AppDomainId":2,"AppDomainAppId":"LMW3SVC2ROOT","MachineName":"WKWIN4480425","Log4NetLevel":"INFO ","HttpRequestNumber":1,"HttpRequestId":"38288a22-96cd-436b-8c54-7deacbc13276"}
{"@t":"2024-04-18T13:17:30.8265487Z","@mt":"{EndMessage} ({Duration}ms) [Timing {TimingId}]","EndMessage":"Completed.","Duration":1191,"TimingId":"9507460","SourceContext":"Umbraco.Web.PublishedCache.NuCache.PublishedSnapshotService","ProcessId":27972,"ProcessName":"iisexpress","ThreadId":1,"AppDomainId":2,"AppDomainAppId":"LMW3SVC2ROOT","MachineName":"WKWIN4480425","Log4NetLevel":"INFO ","HttpRequestNumber":1,"HttpRequestId":"38288a22-96cd-436b-8c54-7deacbc13276"}
{"@t":"2024-04-18T13:17:30.8544728Z","@mt":"{StartMessage} [Timing {TimingId}]","StartMessage":"Loading media from local cache file","TimingId":"8f4c1ba","SourceContext":"Umbraco.Web.PublishedCache.NuCache.PublishedSnapshotService","ProcessId":27972,"ProcessName":"iisexpress","ThreadId":1,"AppDomainId":2,"AppDomainAppId":"LMW3SVC2ROOT","MachineName":"WKWIN4480425","Log4NetLevel":"INFO ","HttpRequestNumber":1,"HttpRequestId":"38288a22-96cd-436b-8c54-7deacbc13276"}
{"@t":"2024-04-18T13:17:31.5027723Z","@mt":"{EndMessage} ({Duration}ms) [Timing {TimingId}]","EndMessage":"Completed.","Duration":648,"TimingId":"8f4c1ba","SourceContext":"Umbraco.Web.PublishedCache.NuCache.PublishedSnapshotService","ProcessId":27972,"ProcessName":"iisexpress","ThreadId":1,"AppDomainId":2,"AppDomainAppId":"LMW3SVC2ROOT","MachineName":"WKWIN4480425","Log4NetLevel":"INFO ","HttpRequestNumber":1,"HttpRequestId":"38288a22-96cd-436b-8c54-7deacbc13276"}
{"@t":"2024-04-18T13:17:32.1128428Z","@mt":"Initializing Umbraco internal event handlers for cache refreshing.","SourceContext":"Umbraco.Web.Cache.DistributedCacheBinderComponent","ProcessId":27972,"ProcessName":"iisexpress","ThreadId":1,"AppDomainId":2,"AppDomainAppId":"LMW3SVC2ROOT","MachineName":"WKWIN4480425","Log4NetLevel":"INFO ","HttpRequestNumber":1,"HttpRequestId":"38288a22-96cd-436b-8c54-7deacbc13276"}
{"@t":"2024-04-18T13:17:32.2973443Z","@mt":"Adding examine event handlers for {RegisteredIndexers} index providers.","RegisteredIndexers":3,"SourceContext":"Umbraco.Web.Search.ExamineComponent","ProcessId":27972,"ProcessName":"iisexpress","ThreadId":1,"AppDomainId":2,"AppDomainAppId":"LMW3SVC2ROOT","MachineName":"WKWIN4480425","Log4NetLevel":"INFO ","HttpRequestNumber":1,"HttpRequestId":"38288a22-96cd-436b-8c54-7deacbc13276"}
{"@t":"2024-04-18T13:17:40.4695374Z","@mt":"Starting '{MigrationName}'...","MigrationName":"Skybrud.Umbraco.Redirects","SourceContext":"Umbraco.Core.Migrations.MigrationPlan","ProcessId":27972,"ProcessName":"iisexpress","ThreadId":1,"AppDomainId":2,"AppDomainAppId":"LMW3SVC2ROOT","MachineName":"WKWIN4480425","Log4NetLevel":"INFO ","HttpRequestNumber":1,"HttpRequestId":"38288a22-96cd-436b-8c54-7deacbc13276"}
{"@t":"2024-04-18T13:17:40.4695374Z","@mt":"At {OrigState}","OrigState":"2.1.1","SourceContext":"Umbraco.Core.Migrations.MigrationPlan","ProcessId":27972,"ProcessName":"iisexpress","ThreadId":1,"AppDomainId":2,"AppDomainAppId":"LMW3SVC2ROOT","MachineName":"WKWIN4480425","Log4NetLevel":"INFO ","HttpRequestNumber":1,"HttpRequestId":"38288a22-96cd-436b-8c54-7deacbc13276"}
{"@t":"2024-04-18T13:17:40.4705356Z","@mt":"Done (pending scope completion).","SourceContext":"Umbraco.Core.Migrations.MigrationPlan","ProcessId":27972,"ProcessName":"iisexpress","ThreadId":1,"AppDomainId":2,"AppDomainAppId":"LMW3SVC2ROOT","MachineName":"WKWIN4480425","Log4NetLevel":"INFO ","HttpRequestNumber":1,"HttpRequestId":"38288a22-96cd-436b-8c54-7deacbc13276"}
{"@t":"2024-04-18T13:17:40.4854951Z","@mt":"Starting initialize async background thread.","SourceContext":"Umbraco.Web.Search.BackgroundIndexRebuilder","ProcessId":27972,"ProcessName":"iisexpress","ThreadId":1,"AppDomainId":2,"AppDomainAppId":"LMW3SVC2ROOT","MachineName":"WKWIN4480425","Log4NetLevel":"INFO ","HttpRequestNumber":1,"HttpRequestId":"38288a22-96cd-436b-8c54-7deacbc13276"}
{"@t":"2024-04-18T13:17:40.4904838Z","@mt":"{EndMessage} ({Duration}ms) [Timing {TimingId}]","EndMessage":"Booted.","Duration":17465,"TimingId":"20af180","SourceContext":"Umbraco.Core.Runtime.CoreRuntime","ProcessId":27972,"ProcessName":"iisexpress","ThreadId":1,"AppDomainId":2,"AppDomainAppId":"LMW3SVC2ROOT","MachineName":"WKWIN4480425","Log4NetLevel":"INFO ","HttpRequestNumber":1,"HttpRequestId":"38288a22-96cd-436b-8c54-7deacbc13276"}
{"@t":"2024-04-18T13:17:41.4848871Z","@mt":"New url {Url} detected, re-discovering application url.","Url":"http://localhost/umbraco","SourceContext":"Umbraco.Core.Sync.ApplicationUrlHelper","ProcessId":27972,"ProcessName":"iisexpress","ThreadId":6,"AppDomainId":2,"AppDomainAppId":"LMW3SVC2ROOT","MachineName":"WKWIN4480425","Log4NetLevel":"INFO ","HttpRequestNumber":2,"HttpRequestId":"bc7c047f-f011-41a0-b1bf-05dbea3a248f"}
{"@t":"2024-04-18T13:17:41.4878812Z","@mt":"ApplicationUrl: {UmbracoAppUrl} (UmbracoModule request)","UmbracoAppUrl":"http://localhost/umbraco","SourceContext":"Umbraco.Core.Sync.ApplicationUrlHelper","ProcessId":27972,"ProcessName":"iisexpress","ThreadId":6,"AppDomainId":2,"AppDomainAppId":"LMW3SVC2ROOT","MachineName":"WKWIN4480425","Log4NetLevel":"INFO ","HttpRequestNumber":2,"HttpRequestId":"bc7c047f-f011-41a0-b1bf-05dbea3a248f"}
{"@t":"2024-04-18T13:17:45.6078352Z","@mt":"The current Document Type {ContentTypeAlias} matches a locally declared controller of type {ControllerName}. Custom Controllers for Umbraco routing must implement '{UmbracoRenderController}' and inherit from '{UmbracoControllerBase}'.","@l":"Warning","ContentTypeAlias":"home","ControllerName":"HPPlc.Controllers.HomeController","UmbracoRenderController":"Umbraco.Web.Mvc.IRenderController","UmbracoControllerBase":"System.Web.Mvc.ControllerBase","SourceContext":"Umbraco.Web.Mvc.RenderRouteHandler","ProcessId":27972,"ProcessName":"iisexpress","ThreadId":6,"AppDomainId":2,"AppDomainAppId":"LMW3SVC2ROOT","MachineName":"WKWIN4480425","Log4NetLevel":"WARN ","HttpRequestNumber":2,"HttpRequestId":"bc7c047f-f011-41a0-b1bf-05dbea3a248f"}
{"@t":"2024-04-18T13:26:39.6555660Z","@mt":"Scheduled health check results:","SourceContext":"Umbraco.Web.HealthCheck.HealthCheckResults","ProcessId":27972,"ProcessName":"iisexpress","ThreadId":39,"AppDomainId":2,"AppDomainAppId":"LMW3SVC2ROOT","MachineName":"WKWIN4480425","Log4NetLevel":"INFO "}
{"@t":"2024-04-18T13:26:39.6565627Z","@mt":"Checks for '{HealthCheckName}' all completed successfully.","HealthCheckName":"Folder & File Permissions","SourceContext":"Umbraco.Web.HealthCheck.HealthCheckResults","ProcessId":27972,"ProcessName":"iisexpress","ThreadId":39,"AppDomainId":2,"AppDomainAppId":"LMW3SVC2ROOT","MachineName":"WKWIN4480425","Log4NetLevel":"INFO "}
{"@t":"2024-04-18T13:26:39.6565627Z","@mt":"Result for {HealthCheckName}: {HealthCheckResult}, Message: '{HealthCheckMessage}'","HealthCheckName":"Folder & File Permissions","HealthCheckResult":"Success","HealthCheckMessage":"All folders have the correct permissions set.","SourceContext":"Umbraco.Web.HealthCheck.HealthCheckResults","ProcessId":27972,"ProcessName":"iisexpress","ThreadId":39,"AppDomainId":2,"AppDomainAppId":"LMW3SVC2ROOT","MachineName":"WKWIN4480425","Log4NetLevel":"INFO "}
{"@t":"2024-04-18T13:26:39.6565627Z","@mt":"Result for {HealthCheckName}: {HealthCheckResult}, Message: '{HealthCheckMessage}'","HealthCheckName":"Folder & File Permissions","HealthCheckResult":"Success","HealthCheckMessage":"All files have the correct permissions set.","SourceContext":"Umbraco.Web.HealthCheck.HealthCheckResults","ProcessId":27972,"ProcessName":"iisexpress","ThreadId":39,"AppDomainId":2,"AppDomainAppId":"LMW3SVC2ROOT","MachineName":"WKWIN4480425","Log4NetLevel":"INFO "}
{"@t":"2024-04-18T13:26:39.6565627Z","@mt":"Checks for '{HealthCheckName}' completed with errors.","@l":"Warning","HealthCheckName":"SMTP Settings","SourceContext":"Umbraco.Web.HealthCheck.HealthCheckResults","ProcessId":27972,"ProcessName":"iisexpress","ThreadId":39,"AppDomainId":2,"AppDomainAppId":"LMW3SVC2ROOT","MachineName":"WKWIN4480425","Log4NetLevel":"WARN "}
{"@t":"2024-04-18T13:26:39.6565627Z","@mt":"Result for {HealthCheckName}: {HealthCheckResult}, Message: '{HealthCheckMessage}'","HealthCheckName":"SMTP Settings","HealthCheckResult":"Error","HealthCheckMessage":"In the Web.config file system.net/mailsettings section, the host is not configured.","SourceContext":"Umbraco.Web.HealthCheck.HealthCheckResults","ProcessId":27972,"ProcessName":"iisexpress","ThreadId":39,"AppDomainId":2,"AppDomainAppId":"LMW3SVC2ROOT","MachineName":"WKWIN4480425","Log4NetLevel":"INFO "}
{"@t":"2024-04-18T13:26:39.6565627Z","@mt":"Checks for '{HealthCheckName}' completed with errors.","@l":"Warning","HealthCheckName":"Macro errors","SourceContext":"Umbraco.Web.HealthCheck.HealthCheckResults","ProcessId":27972,"ProcessName":"iisexpress","ThreadId":39,"AppDomainId":2,"AppDomainAppId":"LMW3SVC2ROOT","MachineName":"WKWIN4480425","Log4NetLevel":"WARN "}
{"@t":"2024-04-18T13:26:39.6565627Z","@mt":"Result for {HealthCheckName}: {HealthCheckResult}, Message: '{HealthCheckMessage}'","HealthCheckName":"Macro errors","HealthCheckResult":"Error","HealthCheckMessage":"MacroErrors are set to 'throw' which will prevent some or all pages in your site from loading completely if there are any errors in macros. Rectifying this will set the value to 'inline'.","SourceContext":"Umbraco.Web.HealthCheck.HealthCheckResults","ProcessId":27972,"ProcessName":"iisexpress","ThreadId":39,"AppDomainId":2,"AppDomainAppId":"LMW3SVC2ROOT","MachineName":"WKWIN4480425","Log4NetLevel":"INFO "}
{"@t":"2024-04-18T13:26:39.6565627Z","@mt":"Checks for '{HealthCheckName}' completed with errors.","@l":"Warning","HealthCheckName":"Notification Email Settings","SourceContext":"Umbraco.Web.HealthCheck.HealthCheckResults","ProcessId":27972,"ProcessName":"iisexpress","ThreadId":39,"AppDomainId":2,"AppDomainAppId":"LMW3SVC2ROOT","MachineName":"WKWIN4480425","Log4NetLevel":"WARN "}
{"@t":"2024-04-18T13:26:39.6565627Z","@mt":"Result for {HealthCheckName}: {HealthCheckResult}, Message: '{HealthCheckMessage}'","HealthCheckName":"Notification Email Settings","HealthCheckResult":"Error","HealthCheckMessage":"Notification email is still set to the default value of <strong>your@email.here</strong>.","SourceContext":"Umbraco.Web.HealthCheck.HealthCheckResults","ProcessId":27972,"ProcessName":"iisexpress","ThreadId":39,"AppDomainId":2,"AppDomainAppId":"LMW3SVC2ROOT","MachineName":"WKWIN4480425","Log4NetLevel":"INFO "}
{"@t":"2024-04-18T13:26:39.6565627Z","@mt":"Checks for '{HealthCheckName}' all completed successfully.","HealthCheckName":"Try Skip IIS Custom Errors","SourceContext":"Umbraco.Web.HealthCheck.HealthCheckResults","ProcessId":27972,"ProcessName":"iisexpress","ThreadId":39,"AppDomainId":2,"AppDomainAppId":"LMW3SVC2ROOT","MachineName":"WKWIN4480425","Log4NetLevel":"INFO "}
{"@t":"2024-04-18T13:26:39.6565627Z","@mt":"Result for {HealthCheckName}: {HealthCheckResult}, Message: '{HealthCheckMessage}'","HealthCheckName":"Try Skip IIS Custom Errors","HealthCheckResult":"Success","HealthCheckMessage":"Try Skip IIS Custom Errors is set to 'true' and you're using IIS version '10.0'.","SourceContext":"Umbraco.Web.HealthCheck.HealthCheckResults","ProcessId":27972,"ProcessName":"iisexpress","ThreadId":39,"AppDomainId":2,"AppDomainAppId":"LMW3SVC2ROOT","MachineName":"WKWIN4480425","Log4NetLevel":"INFO "}
{"@t":"2024-04-18T13:26:39.6565627Z","@mt":"Checks for '{HealthCheckName}' completed with errors.","@l":"Warning","HealthCheckName":"Custom Errors","SourceContext":"Umbraco.Web.HealthCheck.HealthCheckResults","ProcessId":27972,"ProcessName":"iisexpress","ThreadId":39,"AppDomainId":2,"AppDomainAppId":"LMW3SVC2ROOT","MachineName":"WKWIN4480425","Log4NetLevel":"WARN "}
{"@t":"2024-04-18T13:26:39.6565627Z","@mt":"Result for {HealthCheckName}: {HealthCheckResult}, Message: '{HealthCheckMessage}'","HealthCheckName":"Custom Errors","HealthCheckResult":"Error","HealthCheckMessage":"Unable to find <strong>'/configuration/system.web/customErrors/@mode'</strong> in config file <strong>'C:\\Projects\\HP Proj\\HP PLC\\Preprod\\HPPlc_PreProd_Index_BW_Live\\HPPlc\\Web.config'</strong>.","SourceContext":"Umbraco.Web.HealthCheck.HealthCheckResults","ProcessId":27972,"ProcessName":"iisexpress","ThreadId":39,"AppDomainId":2,"AppDomainAppId":"LMW3SVC2ROOT","MachineName":"WKWIN4480425","Log4NetLevel":"INFO "}
{"@t":"2024-04-18T13:26:39.6565627Z","@mt":"Checks for '{HealthCheckName}' all completed successfully.","HealthCheckName":"Trace Mode","SourceContext":"Umbraco.Web.HealthCheck.HealthCheckResults","ProcessId":27972,"ProcessName":"iisexpress","ThreadId":39,"AppDomainId":2,"AppDomainAppId":"LMW3SVC2ROOT","MachineName":"WKWIN4480425","Log4NetLevel":"INFO "}
{"@t":"2024-04-18T13:26:39.6565627Z","@mt":"Result for {HealthCheckName}: {HealthCheckResult}, Message: '{HealthCheckMessage}'","HealthCheckName":"Trace Mode","HealthCheckResult":"Success","HealthCheckMessage":"Trace mode is disabled.","SourceContext":"Umbraco.Web.HealthCheck.HealthCheckResults","ProcessId":27972,"ProcessName":"iisexpress","ThreadId":39,"AppDomainId":2,"AppDomainAppId":"LMW3SVC2ROOT","MachineName":"WKWIN4480425","Log4NetLevel":"INFO "}
{"@t":"2024-04-18T13:26:39.6565627Z","@mt":"Checks for '{HealthCheckName}' completed with errors.","@l":"Warning","HealthCheckName":"Debug Compilation Mode","SourceContext":"Umbraco.Web.HealthCheck.HealthCheckResults","ProcessId":27972,"ProcessName":"iisexpress","ThreadId":39,"AppDomainId":2,"AppDomainAppId":"LMW3SVC2ROOT","MachineName":"WKWIN4480425","Log4NetLevel":"WARN "}
{"@t":"2024-04-18T13:26:39.6565627Z","@mt":"Result for {HealthCheckName}: {HealthCheckResult}, Message: '{HealthCheckMessage}'","HealthCheckName":"Debug Compilation Mode","HealthCheckResult":"Error","HealthCheckMessage":"Debug compilation mode is currently enabled. It is recommended to disable this setting before go live.","SourceContext":"Umbraco.Web.HealthCheck.HealthCheckResults","ProcessId":27972,"ProcessName":"iisexpress","ThreadId":39,"AppDomainId":2,"AppDomainAppId":"LMW3SVC2ROOT","MachineName":"WKWIN4480425","Log4NetLevel":"INFO "}
{"@t":"2024-04-18T13:26:39.6565627Z","@mt":"Checks for '{HealthCheckName}' completed with errors.","@l":"Warning","HealthCheckName":"Cross-site scripting Protection (X-XSS-Protection header)","SourceContext":"Umbraco.Web.HealthCheck.HealthCheckResults","ProcessId":27972,"ProcessName":"iisexpress","ThreadId":39,"AppDomainId":2,"AppDomainAppId":"LMW3SVC2ROOT","MachineName":"WKWIN4480425","Log4NetLevel":"WARN "}
{"@t":"2024-04-18T13:26:39.6565627Z","@mt":"Result for {HealthCheckName}: {HealthCheckResult}, Message: '{HealthCheckMessage}'","HealthCheckName":"Cross-site scripting Protection (X-XSS-Protection header)","HealthCheckResult":"Error","HealthCheckMessage":"Error pinging the URL http://localhost/umbraco - 'The remote server returned an error: (404) Not Found.'","SourceContext":"Umbraco.Web.HealthCheck.HealthCheckResults","ProcessId":27972,"ProcessName":"iisexpress","ThreadId":39,"AppDomainId":2,"AppDomainAppId":"LMW3SVC2ROOT","MachineName":"WKWIN4480425","Log4NetLevel":"INFO "}
{"@t":"2024-04-18T13:26:39.6565627Z","@mt":"Checks for '{HealthCheckName}' completed with errors.","@l":"Warning","HealthCheckName":"Cookie hijacking and protocol downgrade attacks Protection (Strict-Transport-Security Header (HSTS))","SourceContext":"Umbraco.Web.HealthCheck.HealthCheckResults","ProcessId":27972,"ProcessName":"iisexpress","ThreadId":39,"AppDomainId":2,"AppDomainAppId":"LMW3SVC2ROOT","MachineName":"WKWIN4480425","Log4NetLevel":"WARN "}
{"@t":"2024-04-18T13:26:39.6565627Z","@mt":"Result for {HealthCheckName}: {HealthCheckResult}, Message: '{HealthCheckMessage}'","HealthCheckName":"Cookie hijacking and protocol downgrade attacks Protection (Strict-Transport-Security Header (HSTS))","HealthCheckResult":"Error","HealthCheckMessage":"Error pinging the URL http://localhost/umbraco - 'The remote server returned an error: (404) Not Found.'","SourceContext":"Umbraco.Web.HealthCheck.HealthCheckResults","ProcessId":27972,"ProcessName":"iisexpress","ThreadId":39,"AppDomainId":2,"AppDomainAppId":"LMW3SVC2ROOT","MachineName":"WKWIN4480425","Log4NetLevel":"INFO "}
{"@t":"2024-04-18T13:26:39.6565627Z","@mt":"Checks for '{HealthCheckName}' completed with errors.","@l":"Warning","HealthCheckName":"Content/MIME Sniffing Protection","SourceContext":"Umbraco.Web.HealthCheck.HealthCheckResults","ProcessId":27972,"ProcessName":"iisexpress","ThreadId":39,"AppDomainId":2,"AppDomainAppId":"LMW3SVC2ROOT","MachineName":"WKWIN4480425","Log4NetLevel":"WARN "}
{"@t":"2024-04-18T13:26:39.6565627Z","@mt":"Result for {HealthCheckName}: {HealthCheckResult}, Message: '{HealthCheckMessage}'","HealthCheckName":"Content/MIME Sniffing Protection","HealthCheckResult":"Error","HealthCheckMessage":"Error pinging the URL http://localhost/umbraco - 'The remote server returned an error: (404) Not Found.'","SourceContext":"Umbraco.Web.HealthCheck.HealthCheckResults","ProcessId":27972,"ProcessName":"iisexpress","ThreadId":39,"AppDomainId":2,"AppDomainAppId":"LMW3SVC2ROOT","MachineName":"WKWIN4480425","Log4NetLevel":"INFO "}
{"@t":"2024-04-18T13:26:39.6565627Z","@mt":"Checks for '{HealthCheckName}' completed with errors.","@l":"Warning","HealthCheckName":"Excessive Headers","SourceContext":"Umbraco.Web.HealthCheck.HealthCheckResults","ProcessId":27972,"ProcessName":"iisexpress","ThreadId":39,"AppDomainId":2,"AppDomainAppId":"LMW3SVC2ROOT","MachineName":"WKWIN4480425","Log4NetLevel":"WARN "}
{"@t":"2024-04-18T13:26:39.6565627Z","@mt":"Result for {HealthCheckName}: {HealthCheckResult}, Message: '{HealthCheckMessage}'","HealthCheckName":"Excessive Headers","HealthCheckResult":"Warning","HealthCheckMessage":"[httpsCheckInvalidUrl]","SourceContext":"Umbraco.Web.HealthCheck.HealthCheckResults","ProcessId":27972,"ProcessName":"iisexpress","ThreadId":39,"AppDomainId":2,"AppDomainAppId":"LMW3SVC2ROOT","MachineName":"WKWIN4480425","Log4NetLevel":"INFO "}
{"@t":"2024-04-18T13:26:39.6565627Z","@mt":"Checks for '{HealthCheckName}' completed with errors.","@l":"Warning","HealthCheckName":"Click-Jacking Protection","SourceContext":"Umbraco.Web.HealthCheck.HealthCheckResults","ProcessId":27972,"ProcessName":"iisexpress","ThreadId":39,"AppDomainId":2,"AppDomainAppId":"LMW3SVC2ROOT","MachineName":"WKWIN4480425","Log4NetLevel":"WARN "}
{"@t":"2024-04-18T13:26:39.6565627Z","@mt":"Result for {HealthCheckName}: {HealthCheckResult}, Message: '{HealthCheckMessage}'","HealthCheckName":"Click-Jacking Protection","HealthCheckResult":"Error","HealthCheckMessage":"Error pinging the URL http://localhost/umbraco - 'The remote server returned an error: (404) Not Found.'","SourceContext":"Umbraco.Web.HealthCheck.HealthCheckResults","ProcessId":27972,"ProcessName":"iisexpress","ThreadId":39,"AppDomainId":2,"AppDomainAppId":"LMW3SVC2ROOT","MachineName":"WKWIN4480425","Log4NetLevel":"INFO "}
{"@t":"2024-04-18T13:26:39.6565627Z","@mt":"Checks for '{HealthCheckName}' completed with errors.","@l":"Warning","HealthCheckName":"HTTPS Configuration","SourceContext":"Umbraco.Web.HealthCheck.HealthCheckResults","ProcessId":27972,"ProcessName":"iisexpress","ThreadId":39,"AppDomainId":2,"AppDomainAppId":"LMW3SVC2ROOT","MachineName":"WKWIN4480425","Log4NetLevel":"WARN "}
{"@t":"2024-04-18T13:26:39.6565627Z","@mt":"Result for {HealthCheckName}: {HealthCheckResult}, Message: '{HealthCheckMessage}'","HealthCheckName":"HTTPS Configuration","HealthCheckResult":"Error","HealthCheckMessage":"You are currently not viewing the site using the HTTPS scheme.","SourceContext":"Umbraco.Web.HealthCheck.HealthCheckResults","ProcessId":27972,"ProcessName":"iisexpress","ThreadId":39,"AppDomainId":2,"AppDomainAppId":"LMW3SVC2ROOT","MachineName":"WKWIN4480425","Log4NetLevel":"INFO "}
{"@t":"2024-04-18T13:26:39.6575648Z","@mt":"Result for {HealthCheckName}: {HealthCheckResult}, Message: '{HealthCheckMessage}'","HealthCheckName":"HTTPS Configuration","HealthCheckResult":"Info","HealthCheckMessage":"The appSetting 'Umbraco.Core.UseHttps' is set to 'false' in your web.config file. Once you access this site using the HTTPS scheme, that should be set to 'true'.","SourceContext":"Umbraco.Web.HealthCheck.HealthCheckResults","ProcessId":27972,"ProcessName":"iisexpress","ThreadId":39,"AppDomainId":2,"AppDomainAppId":"LMW3SVC2ROOT","MachineName":"WKWIN4480425","Log4NetLevel":"INFO "}
{"@t":"2024-04-18T13:26:39.6575648Z","@mt":"Result for {HealthCheckName}: {HealthCheckResult}, Message: '{HealthCheckMessage}'","HealthCheckName":"HTTPS Configuration","HealthCheckResult":"Error","HealthCheckMessage":"Error pinging the URL https://localhost/umbraco - 'The underlying connection was closed: An unexpected error occurred on a send.'","SourceContext":"Umbraco.Web.HealthCheck.HealthCheckResults","ProcessId":27972,"ProcessName":"iisexpress","ThreadId":39,"AppDomainId":2,"AppDomainAppId":"LMW3SVC2ROOT","MachineName":"WKWIN4480425","Log4NetLevel":"INFO "}
{"@t":"2024-04-18T13:26:39.6575648Z","@mt":"Checks for '{HealthCheckName}' all completed successfully.","HealthCheckName":"Database data integrity check","SourceContext":"Umbraco.Web.HealthCheck.HealthCheckResults","ProcessId":27972,"ProcessName":"iisexpress","ThreadId":39,"AppDomainId":2,"AppDomainAppId":"LMW3SVC2ROOT","MachineName":"WKWIN4480425","Log4NetLevel":"INFO "}
{"@t":"2024-04-18T13:26:39.6575648Z","@mt":"Result for {HealthCheckName}: {HealthCheckResult}, Message: '{HealthCheckMessage}'","HealthCheckName":"Database data integrity check","HealthCheckResult":"Success","HealthCheckMessage":"<p>All document paths are valid</p>\r\n","SourceContext":"Umbraco.Web.HealthCheck.HealthCheckResults","ProcessId":27972,"ProcessName":"iisexpress","ThreadId":39,"AppDomainId":2,"AppDomainAppId":"LMW3SVC2ROOT","MachineName":"WKWIN4480425","Log4NetLevel":"INFO "}
{"@t":"2024-04-18T13:26:39.6575648Z","@mt":"Result for {HealthCheckName}: {HealthCheckResult}, Message: '{HealthCheckMessage}'","HealthCheckName":"Database data integrity check","HealthCheckResult":"Success","HealthCheckMessage":"<p>All media paths are valid</p>\r\n","SourceContext":"Umbraco.Web.HealthCheck.HealthCheckResults","ProcessId":27972,"ProcessName":"iisexpress","ThreadId":39,"AppDomainId":2,"AppDomainAppId":"LMW3SVC2ROOT","MachineName":"WKWIN4480425","Log4NetLevel":"INFO "}
{"@t":"2024-04-18T13:28:16.5157896Z","@mt":"On Registration - SubscriptionMailer","@l":"Error","@x":"System.Net.Mail.SmtpException: Failure sending mail. ---> System.Net.WebException: Unable to connect to the remote server ---> System.Net.Sockets.SocketException: A connection attempt failed because the connected party did not properly respond after a period of time, or established connection failed because connected host has failed to respond 54.185.234.152:587\r\n   at System.Net.Sockets.Socket.DoConnect(EndPoint endPointSnapshot, SocketAddress socketAddress)\r\n   at System.Net.ServicePoint.ConnectSocketInternal(Boolean connectFailure, Socket s4, Socket s6, Socket& socket, IPAddress& address, ConnectSocketState state, IAsyncResult asyncResult, Exception& exception)\r\n   --- End of inner exception stack trace ---\r\n   at System.Net.ServicePoint.GetConnection(PooledStream PooledStream, Object owner, Boolean async, IPAddress& address, Socket& abortSocket, Socket& abortSocket6)\r\n   at System.Net.PooledStream.Activate(Object owningObject, Boolean async, GeneralAsyncDelegate asyncCallback)\r\n   at System.Net.PooledStream.Activate(Object owningObject, GeneralAsyncDelegate asyncCallback)\r\n   at System.Net.ConnectionPool.GetConnection(Object owningObject, GeneralAsyncDelegate asyncCallback, Int32 creationTimeout)\r\n   at System.Net.Mail.SmtpConnection.GetConnection(ServicePoint servicePoint)\r\n   at System.Net.Mail.SmtpTransport.GetConnection(ServicePoint servicePoint)\r\n   at System.Net.Mail.SmtpClient.GetConnection()\r\n   at System.Net.Mail.SmtpClient.Send(MailMessage message)\r\n   --- End of inner exception stack trace ---\r\n   at HPPlc.Models.Mailer.SenderMailer.SendPaymentEmailerContent(String subject, String To, String body, IEnumerable`1 CC, IEnumerable`1 BCC)\r\n   at HPPlc.Controllers.SubscriptionController.SubscriptionEmailer(Int32 ranking, String PaymentId, String invoicepdf, String email, String AgeGroup)\r\n   at HPPlc.Controllers.HomeController.Welcomemail(Int32 UserId, String _email)","SourceContext":"Umbraco.Web.PublishedModels.HomeContainer","ProcessId":27972,"ProcessName":"iisexpress","ThreadId":6,"AppDomainId":2,"AppDomainAppId":"LMW3SVC2ROOT","MachineName":"WKWIN4480425","Log4NetLevel":"ERROR","HttpRequestNumber":3,"HttpRequestId":"6c7de44b-d112-4f11-ac32-f4ccb0069ab5"}
{"@t":"2024-04-18T13:35:22.8720529Z","@mt":"On Registration - SubscriptionMailer","@l":"Error","@x":"System.Net.Mail.SmtpException: Failure sending mail. ---> System.Net.WebException: Unable to connect to the remote server ---> System.Net.Sockets.SocketException: A connection attempt failed because the connected party did not properly respond after a period of time, or established connection failed because connected host has failed to respond 44.225.148.59:587\r\n   at System.Net.Sockets.Socket.DoConnect(EndPoint endPointSnapshot, SocketAddress socketAddress)\r\n   at System.Net.ServicePoint.ConnectSocketInternal(Boolean connectFailure, Socket s4, Socket s6, Socket& socket, IPAddress& address, ConnectSocketState state, IAsyncResult asyncResult, Exception& exception)\r\n   --- End of inner exception stack trace ---\r\n   at System.Net.ServicePoint.GetConnection(PooledStream PooledStream, Object owner, Boolean async, IPAddress& address, Socket& abortSocket, Socket& abortSocket6)\r\n   at System.Net.PooledStream.Activate(Object owningObject, Boolean async, GeneralAsyncDelegate asyncCallback)\r\n   at System.Net.PooledStream.Activate(Object owningObject, GeneralAsyncDelegate asyncCallback)\r\n   at System.Net.ConnectionPool.GetConnection(Object owningObject, GeneralAsyncDelegate asyncCallback, Int32 creationTimeout)\r\n   at System.Net.Mail.SmtpConnection.GetConnection(ServicePoint servicePoint)\r\n   at System.Net.Mail.SmtpTransport.GetConnection(ServicePoint servicePoint)\r\n   at System.Net.Mail.SmtpClient.GetConnection()\r\n   at System.Net.Mail.SmtpClient.Send(MailMessage message)\r\n   --- End of inner exception stack trace ---\r\n   at HPPlc.Models.Mailer.SenderMailer.SendPaymentEmailerContent(String subject, String To, String body, IEnumerable`1 CC, IEnumerable`1 BCC)\r\n   at HPPlc.Controllers.SubscriptionController.SubscriptionEmailer(Int32 ranking, String PaymentId, String invoicepdf, String email, String AgeGroup)\r\n   at HPPlc.Controllers.HomeController.Welcomemail(Int32 UserId, String _email)","SourceContext":"Umbraco.Web.PublishedModels.HomeContainer","ProcessId":27972,"ProcessName":"iisexpress","ThreadId":44,"AppDomainId":2,"AppDomainAppId":"LMW3SVC2ROOT","MachineName":"WKWIN4480425","Log4NetLevel":"ERROR","HttpRequestNumber":4,"HttpRequestId":"3c06cf5f-59e5-44e6-beca-991aba9cce3f"}
{"@t":"2024-04-18T14:05:10.6044074Z","@mt":"On Registration - SubscriptionMailer","@l":"Error","@x":"System.Net.Mail.SmtpException: The SMTP server requires a secure connection or the client was not authenticated. The server response was: Authentication required\r\n   at HPPlc.Models.Mailer.SenderMailer.SendPaymentEmailerContent(String subject, String To, String body, IEnumerable`1 CC, IEnumerable`1 BCC)\r\n   at HPPlc.Controllers.SubscriptionController.SubscriptionEmailer(Int32 ranking, String PaymentId, String invoicepdf, String email, String AgeGroup)\r\n   at HPPlc.Controllers.HomeController.Welcomemail(Int32 UserId, String _email)","SourceContext":"Umbraco.Web.PublishedModels.HomeContainer","ProcessId":27972,"ProcessName":"iisexpress","ThreadId":55,"AppDomainId":2,"AppDomainAppId":"LMW3SVC2ROOT","MachineName":"WKWIN4480425","Log4NetLevel":"ERROR","HttpRequestNumber":5,"HttpRequestId":"8c4ecc89-2073-4005-9e68-e9117a9b58a3"}
