{"@t":"2024-01-09T08:07:56.8559298Z","@mt":"{StartMessage} [Timing {TimingId}]","StartMessage":"Booting Umbraco 8.12.2.","TimingId":"46dbbc4","SourceContext":"Umbraco.Core.Runtime.CoreRuntime","ProcessId":11612,"ProcessName":"iisexpress","ThreadId":1,"AppDomainId":2,"AppDomainAppId":"LMW3SVC2ROOT","MachineName":"WKWIN4480425","Log4NetLevel":"INFO ","HttpRequestNumber":1,"HttpRequestId":"f035f706-54e3-4fb0-9cac-daebeda1edcb"}
{"@t":"2024-01-09T08:07:56.8816296Z","@mt":"Booting site '{HostingSiteName}', app '{HostingApplicationID}', path '{HostingPhysicalPath}', server '{MachineName}'.","HostingSiteName":"HPPlc","HostingApplicationID":"/LM/W3SVC/2/ROOT","HostingPhysicalPath":"C:\\Projects\\HP Proj\\HP PLC\\Preprod\\HPPlc_PreProd_Index_BW\\HPPlc\\","MachineName":"WKWIN4480425","SourceContext":"Umbraco.Core.Runtime.CoreRuntime","ProcessId":11612,"ProcessName":"iisexpress","ThreadId":1,"AppDomainId":2,"AppDomainAppId":"LMW3SVC2ROOT","Log4NetLevel":"INFO ","HttpRequestNumber":1,"HttpRequestId":"f035f706-54e3-4fb0-9cac-daebeda1edcb"}
{"@t":"2024-01-09T08:07:56.9816978Z","@mt":"Acquiring.","SourceContext":"Umbraco.Core.Runtime.MainDom","ProcessId":11612,"ProcessName":"iisexpress","ThreadId":1,"AppDomainId":2,"AppDomainAppId":"LMW3SVC2ROOT","MachineName":"WKWIN4480425","Log4NetLevel":"INFO ","HttpRequestNumber":1,"HttpRequestId":"f035f706-54e3-4fb0-9cac-daebeda1edcb"}
{"@t":"2024-01-09T08:07:56.9837051Z","@mt":"Acquired.","SourceContext":"Umbraco.Core.Runtime.MainDom","ProcessId":11612,"ProcessName":"iisexpress","ThreadId":1,"AppDomainId":2,"AppDomainAppId":"LMW3SVC2ROOT","MachineName":"WKWIN4480425","Log4NetLevel":"INFO ","HttpRequestNumber":1,"HttpRequestId":"f035f706-54e3-4fb0-9cac-daebeda1edcb"}
{"@t":"2024-01-09T08:07:58.5312514Z","@mt":"{StartMessage} [Timing {TimingId}]","StartMessage":"Resolving composer types.","TimingId":"7f123e1","SourceContext":"Umbraco.Core.Runtime.CoreRuntime","ProcessId":11612,"ProcessName":"iisexpress","ThreadId":1,"AppDomainId":2,"AppDomainAppId":"LMW3SVC2ROOT","MachineName":"WKWIN4480425","Log4NetLevel":"INFO ","HttpRequestNumber":1,"HttpRequestId":"f035f706-54e3-4fb0-9cac-daebeda1edcb"}
{"@t":"2024-01-09T08:07:58.7867315Z","@mt":"{EndMessage} ({Duration}ms) [Timing {TimingId}]","EndMessage":"Resolved.","Duration":255,"TimingId":"7f123e1","SourceContext":"Umbraco.Core.Runtime.CoreRuntime","ProcessId":11612,"ProcessName":"iisexpress","ThreadId":1,"AppDomainId":2,"AppDomainAppId":"LMW3SVC2ROOT","MachineName":"WKWIN4480425","Log4NetLevel":"INFO ","HttpRequestNumber":1,"HttpRequestId":"f035f706-54e3-4fb0-9cac-daebeda1edcb"}
{"@t":"2024-01-09T08:07:59.7014299Z","@mt":"Registered with MainDom, localContentDbExists? {LocalContentDbExists}, localMediaDbExists? {LocalMediaDbExists}","LocalContentDbExists":true,"LocalMediaDbExists":true,"SourceContext":"Umbraco.Web.PublishedCache.NuCache.PublishedSnapshotService","ProcessId":11612,"ProcessName":"iisexpress","ThreadId":1,"AppDomainId":2,"AppDomainAppId":"LMW3SVC2ROOT","MachineName":"WKWIN4480425","Log4NetLevel":"INFO ","HttpRequestNumber":1,"HttpRequestId":"f035f706-54e3-4fb0-9cac-daebeda1edcb"}
{"@t":"2024-01-09T08:07:59.7014299Z","@mt":"Creating the content store, localContentDbExists? {LocalContentDbExists}","LocalContentDbExists":true,"SourceContext":"Umbraco.Web.PublishedCache.NuCache.PublishedSnapshotService","ProcessId":11612,"ProcessName":"iisexpress","ThreadId":1,"AppDomainId":2,"AppDomainAppId":"LMW3SVC2ROOT","MachineName":"WKWIN4480425","Log4NetLevel":"INFO ","HttpRequestNumber":1,"HttpRequestId":"f035f706-54e3-4fb0-9cac-daebeda1edcb"}
{"@t":"2024-01-09T08:07:59.7034265Z","@mt":"Creating the media store, localMediaDbExists? {LocalMediaDbExists}","LocalMediaDbExists":true,"SourceContext":"Umbraco.Web.PublishedCache.NuCache.PublishedSnapshotService","ProcessId":11612,"ProcessName":"iisexpress","ThreadId":1,"AppDomainId":2,"AppDomainAppId":"LMW3SVC2ROOT","MachineName":"WKWIN4480425","Log4NetLevel":"INFO ","HttpRequestNumber":1,"HttpRequestId":"f035f706-54e3-4fb0-9cac-daebeda1edcb"}
{"@t":"2024-01-09T08:08:00.3052191Z","@mt":"{StartMessage} [Timing {TimingId}]","StartMessage":"Loading content from local cache file","TimingId":"73695c6","SourceContext":"Umbraco.Web.PublishedCache.NuCache.PublishedSnapshotService","ProcessId":11612,"ProcessName":"iisexpress","ThreadId":1,"AppDomainId":2,"AppDomainAppId":"LMW3SVC2ROOT","MachineName":"WKWIN4480425","Log4NetLevel":"INFO ","HttpRequestNumber":1,"HttpRequestId":"f035f706-54e3-4fb0-9cac-daebeda1edcb"}
{"@t":"2024-01-09T08:08:01.2218397Z","@mt":"{EndMessage} ({Duration}ms) [Timing {TimingId}]","EndMessage":"Completed.","Duration":916,"TimingId":"73695c6","SourceContext":"Umbraco.Web.PublishedCache.NuCache.PublishedSnapshotService","ProcessId":11612,"ProcessName":"iisexpress","ThreadId":1,"AppDomainId":2,"AppDomainAppId":"LMW3SVC2ROOT","MachineName":"WKWIN4480425","Log4NetLevel":"INFO ","HttpRequestNumber":1,"HttpRequestId":"f035f706-54e3-4fb0-9cac-daebeda1edcb"}
{"@t":"2024-01-09T08:08:01.2387951Z","@mt":"{StartMessage} [Timing {TimingId}]","StartMessage":"Loading media from local cache file","TimingId":"b49e8fc","SourceContext":"Umbraco.Web.PublishedCache.NuCache.PublishedSnapshotService","ProcessId":11612,"ProcessName":"iisexpress","ThreadId":1,"AppDomainId":2,"AppDomainAppId":"LMW3SVC2ROOT","MachineName":"WKWIN4480425","Log4NetLevel":"INFO ","HttpRequestNumber":1,"HttpRequestId":"f035f706-54e3-4fb0-9cac-daebeda1edcb"}
{"@t":"2024-01-09T08:08:01.6375276Z","@mt":"{EndMessage} ({Duration}ms) [Timing {TimingId}]","EndMessage":"Completed.","Duration":398,"TimingId":"b49e8fc","SourceContext":"Umbraco.Web.PublishedCache.NuCache.PublishedSnapshotService","ProcessId":11612,"ProcessName":"iisexpress","ThreadId":1,"AppDomainId":2,"AppDomainAppId":"LMW3SVC2ROOT","MachineName":"WKWIN4480425","Log4NetLevel":"INFO ","HttpRequestNumber":1,"HttpRequestId":"f035f706-54e3-4fb0-9cac-daebeda1edcb"}
{"@t":"2024-01-09T08:08:01.9831453Z","@mt":"Initializing Umbraco internal event handlers for cache refreshing.","SourceContext":"Umbraco.Web.Cache.DistributedCacheBinderComponent","ProcessId":11612,"ProcessName":"iisexpress","ThreadId":1,"AppDomainId":2,"AppDomainAppId":"LMW3SVC2ROOT","MachineName":"WKWIN4480425","Log4NetLevel":"INFO ","HttpRequestNumber":1,"HttpRequestId":"f035f706-54e3-4fb0-9cac-daebeda1edcb"}
{"@t":"2024-01-09T08:08:02.0896945Z","@mt":"Adding examine event handlers for {RegisteredIndexers} index providers.","RegisteredIndexers":3,"SourceContext":"Umbraco.Web.Search.ExamineComponent","ProcessId":11612,"ProcessName":"iisexpress","ThreadId":1,"AppDomainId":2,"AppDomainAppId":"LMW3SVC2ROOT","MachineName":"WKWIN4480425","Log4NetLevel":"INFO ","HttpRequestNumber":1,"HttpRequestId":"f035f706-54e3-4fb0-9cac-daebeda1edcb"}
{"@t":"2024-01-09T08:08:05.7755914Z","@mt":"Starting '{MigrationName}'...","MigrationName":"Skybrud.Umbraco.Redirects","SourceContext":"Umbraco.Core.Migrations.MigrationPlan","ProcessId":11612,"ProcessName":"iisexpress","ThreadId":1,"AppDomainId":2,"AppDomainAppId":"LMW3SVC2ROOT","MachineName":"WKWIN4480425","Log4NetLevel":"INFO ","HttpRequestNumber":1,"HttpRequestId":"f035f706-54e3-4fb0-9cac-daebeda1edcb"}
{"@t":"2024-01-09T08:08:05.7755914Z","@mt":"At {OrigState}","OrigState":"2.1.1","SourceContext":"Umbraco.Core.Migrations.MigrationPlan","ProcessId":11612,"ProcessName":"iisexpress","ThreadId":1,"AppDomainId":2,"AppDomainAppId":"LMW3SVC2ROOT","MachineName":"WKWIN4480425","Log4NetLevel":"INFO ","HttpRequestNumber":1,"HttpRequestId":"f035f706-54e3-4fb0-9cac-daebeda1edcb"}
{"@t":"2024-01-09T08:08:05.7755914Z","@mt":"Done (pending scope completion).","SourceContext":"Umbraco.Core.Migrations.MigrationPlan","ProcessId":11612,"ProcessName":"iisexpress","ThreadId":1,"AppDomainId":2,"AppDomainAppId":"LMW3SVC2ROOT","MachineName":"WKWIN4480425","Log4NetLevel":"INFO ","HttpRequestNumber":1,"HttpRequestId":"f035f706-54e3-4fb0-9cac-daebeda1edcb"}
{"@t":"2024-01-09T08:08:05.7835701Z","@mt":"Starting initialize async background thread.","SourceContext":"Umbraco.Web.Search.BackgroundIndexRebuilder","ProcessId":11612,"ProcessName":"iisexpress","ThreadId":1,"AppDomainId":2,"AppDomainAppId":"LMW3SVC2ROOT","MachineName":"WKWIN4480425","Log4NetLevel":"INFO ","HttpRequestNumber":1,"HttpRequestId":"f035f706-54e3-4fb0-9cac-daebeda1edcb"}
{"@t":"2024-01-09T08:08:05.7865609Z","@mt":"{EndMessage} ({Duration}ms) [Timing {TimingId}]","EndMessage":"Booted.","Duration":8940,"TimingId":"46dbbc4","SourceContext":"Umbraco.Core.Runtime.CoreRuntime","ProcessId":11612,"ProcessName":"iisexpress","ThreadId":1,"AppDomainId":2,"AppDomainAppId":"LMW3SVC2ROOT","MachineName":"WKWIN4480425","Log4NetLevel":"INFO ","HttpRequestNumber":1,"HttpRequestId":"f035f706-54e3-4fb0-9cac-daebeda1edcb"}
{"@t":"2024-01-09T08:08:06.2103924Z","@mt":"New url {Url} detected, re-discovering application url.","Url":"http://localhost/umbraco","SourceContext":"Umbraco.Core.Sync.ApplicationUrlHelper","ProcessId":11612,"ProcessName":"iisexpress","ThreadId":6,"AppDomainId":2,"AppDomainAppId":"LMW3SVC2ROOT","MachineName":"WKWIN4480425","Log4NetLevel":"INFO ","HttpRequestNumber":2,"HttpRequestId":"afe4b6e5-98aa-46a1-bede-224f666caabb"}
{"@t":"2024-01-09T08:08:06.2133829Z","@mt":"ApplicationUrl: {UmbracoAppUrl} (UmbracoModule request)","UmbracoAppUrl":"http://localhost/umbraco","SourceContext":"Umbraco.Core.Sync.ApplicationUrlHelper","ProcessId":11612,"ProcessName":"iisexpress","ThreadId":6,"AppDomainId":2,"AppDomainAppId":"LMW3SVC2ROOT","MachineName":"WKWIN4480425","Log4NetLevel":"INFO ","HttpRequestNumber":2,"HttpRequestId":"afe4b6e5-98aa-46a1-bede-224f666caabb"}
{"@t":"2024-01-09T08:08:08.0748346Z","@mt":"The current Document Type {ContentTypeAlias} matches a locally declared controller of type {ControllerName}. Custom Controllers for Umbraco routing must implement '{UmbracoRenderController}' and inherit from '{UmbracoControllerBase}'.","@l":"Warning","ContentTypeAlias":"home","ControllerName":"HPPlc.Controllers.HomeController","UmbracoRenderController":"Umbraco.Web.Mvc.IRenderController","UmbracoControllerBase":"System.Web.Mvc.ControllerBase","SourceContext":"Umbraco.Web.Mvc.RenderRouteHandler","ProcessId":11612,"ProcessName":"iisexpress","ThreadId":6,"AppDomainId":2,"AppDomainAppId":"LMW3SVC2ROOT","MachineName":"WKWIN4480425","Log4NetLevel":"WARN ","HttpRequestNumber":2,"HttpRequestId":"afe4b6e5-98aa-46a1-bede-224f666caabb"}
{"@t":"2024-01-09T08:10:17.3394447Z","@mt":"{StartMessage} [Timing {TimingId}]","StartMessage":"Booting Umbraco 8.12.2.","TimingId":"c56b684","SourceContext":"Umbraco.Core.Runtime.CoreRuntime","ProcessId":23180,"ProcessName":"iisexpress","ThreadId":1,"AppDomainId":2,"AppDomainAppId":"LMW3SVC2ROOT","MachineName":"WKWIN4480425","Log4NetLevel":"INFO ","HttpRequestNumber":1,"HttpRequestId":"f5152d61-9d51-455c-9e1e-8b03ba11003d"}
{"@t":"2024-01-09T08:10:17.3743515Z","@mt":"Booting site '{HostingSiteName}', app '{HostingApplicationID}', path '{HostingPhysicalPath}', server '{MachineName}'.","HostingSiteName":"HPPlc","HostingApplicationID":"/LM/W3SVC/2/ROOT","HostingPhysicalPath":"C:\\Projects\\HP Proj\\HP PLC\\Preprod\\HPPlc_PreProd_Index_BW\\HPPlc\\","MachineName":"WKWIN4480425","SourceContext":"Umbraco.Core.Runtime.CoreRuntime","ProcessId":23180,"ProcessName":"iisexpress","ThreadId":1,"AppDomainId":2,"AppDomainAppId":"LMW3SVC2ROOT","Log4NetLevel":"INFO ","HttpRequestNumber":1,"HttpRequestId":"f5152d61-9d51-455c-9e1e-8b03ba11003d"}
{"@t":"2024-01-09T08:10:17.5050026Z","@mt":"Acquiring.","SourceContext":"Umbraco.Core.Runtime.MainDom","ProcessId":23180,"ProcessName":"iisexpress","ThreadId":1,"AppDomainId":2,"AppDomainAppId":"LMW3SVC2ROOT","MachineName":"WKWIN4480425","Log4NetLevel":"INFO ","HttpRequestNumber":1,"HttpRequestId":"f5152d61-9d51-455c-9e1e-8b03ba11003d"}
{"@t":"2024-01-09T08:10:17.5079928Z","@mt":"Acquired.","SourceContext":"Umbraco.Core.Runtime.MainDom","ProcessId":23180,"ProcessName":"iisexpress","ThreadId":1,"AppDomainId":2,"AppDomainAppId":"LMW3SVC2ROOT","MachineName":"WKWIN4480425","Log4NetLevel":"INFO ","HttpRequestNumber":1,"HttpRequestId":"f5152d61-9d51-455c-9e1e-8b03ba11003d"}
{"@t":"2024-01-09T08:10:19.4174003Z","@mt":"{StartMessage} [Timing {TimingId}]","StartMessage":"Resolving composer types.","TimingId":"493c3ad","SourceContext":"Umbraco.Core.Runtime.CoreRuntime","ProcessId":23180,"ProcessName":"iisexpress","ThreadId":1,"AppDomainId":2,"AppDomainAppId":"LMW3SVC2ROOT","MachineName":"WKWIN4480425","Log4NetLevel":"INFO ","HttpRequestNumber":1,"HttpRequestId":"f5152d61-9d51-455c-9e1e-8b03ba11003d"}
{"@t":"2024-01-09T08:10:19.9330146Z","@mt":"{EndMessage} ({Duration}ms) [Timing {TimingId}]","EndMessage":"Resolved.","Duration":513,"TimingId":"493c3ad","SourceContext":"Umbraco.Core.Runtime.CoreRuntime","ProcessId":23180,"ProcessName":"iisexpress","ThreadId":1,"AppDomainId":2,"AppDomainAppId":"LMW3SVC2ROOT","MachineName":"WKWIN4480425","Log4NetLevel":"INFO ","HttpRequestNumber":1,"HttpRequestId":"f5152d61-9d51-455c-9e1e-8b03ba11003d"}
{"@t":"2024-01-09T08:10:21.3202397Z","@mt":"Registered with MainDom, localContentDbExists? {LocalContentDbExists}, localMediaDbExists? {LocalMediaDbExists}","LocalContentDbExists":true,"LocalMediaDbExists":true,"SourceContext":"Umbraco.Web.PublishedCache.NuCache.PublishedSnapshotService","ProcessId":23180,"ProcessName":"iisexpress","ThreadId":1,"AppDomainId":2,"AppDomainAppId":"LMW3SVC2ROOT","MachineName":"WKWIN4480425","Log4NetLevel":"INFO ","HttpRequestNumber":1,"HttpRequestId":"f5152d61-9d51-455c-9e1e-8b03ba11003d"}
{"@t":"2024-01-09T08:10:21.3202397Z","@mt":"Creating the content store, localContentDbExists? {LocalContentDbExists}","LocalContentDbExists":true,"SourceContext":"Umbraco.Web.PublishedCache.NuCache.PublishedSnapshotService","ProcessId":23180,"ProcessName":"iisexpress","ThreadId":1,"AppDomainId":2,"AppDomainAppId":"LMW3SVC2ROOT","MachineName":"WKWIN4480425","Log4NetLevel":"INFO ","HttpRequestNumber":1,"HttpRequestId":"f5152d61-9d51-455c-9e1e-8b03ba11003d"}
{"@t":"2024-01-09T08:10:21.3252266Z","@mt":"Creating the media store, localMediaDbExists? {LocalMediaDbExists}","LocalMediaDbExists":true,"SourceContext":"Umbraco.Web.PublishedCache.NuCache.PublishedSnapshotService","ProcessId":23180,"ProcessName":"iisexpress","ThreadId":1,"AppDomainId":2,"AppDomainAppId":"LMW3SVC2ROOT","MachineName":"WKWIN4480425","Log4NetLevel":"INFO ","HttpRequestNumber":1,"HttpRequestId":"f5152d61-9d51-455c-9e1e-8b03ba11003d"}
{"@t":"2024-01-09T08:10:22.2339938Z","@mt":"{StartMessage} [Timing {TimingId}]","StartMessage":"Loading content from local cache file","TimingId":"d2f44b8","SourceContext":"Umbraco.Web.PublishedCache.NuCache.PublishedSnapshotService","ProcessId":23180,"ProcessName":"iisexpress","ThreadId":1,"AppDomainId":2,"AppDomainAppId":"LMW3SVC2ROOT","MachineName":"WKWIN4480425","Log4NetLevel":"INFO ","HttpRequestNumber":1,"HttpRequestId":"f5152d61-9d51-455c-9e1e-8b03ba11003d"}
{"@t":"2024-01-09T08:10:23.1016612Z","@mt":"{EndMessage} ({Duration}ms) [Timing {TimingId}]","EndMessage":"Completed.","Duration":867,"TimingId":"d2f44b8","SourceContext":"Umbraco.Web.PublishedCache.NuCache.PublishedSnapshotService","ProcessId":23180,"ProcessName":"iisexpress","ThreadId":1,"AppDomainId":2,"AppDomainAppId":"LMW3SVC2ROOT","MachineName":"WKWIN4480425","Log4NetLevel":"INFO ","HttpRequestNumber":1,"HttpRequestId":"f5152d61-9d51-455c-9e1e-8b03ba11003d"}
{"@t":"2024-01-09T08:10:23.1202941Z","@mt":"{StartMessage} [Timing {TimingId}]","StartMessage":"Loading media from local cache file","TimingId":"86eb2b1","SourceContext":"Umbraco.Web.PublishedCache.NuCache.PublishedSnapshotService","ProcessId":23180,"ProcessName":"iisexpress","ThreadId":1,"AppDomainId":2,"AppDomainAppId":"LMW3SVC2ROOT","MachineName":"WKWIN4480425","Log4NetLevel":"INFO ","HttpRequestNumber":1,"HttpRequestId":"f5152d61-9d51-455c-9e1e-8b03ba11003d"}
{"@t":"2024-01-09T08:10:23.5633182Z","@mt":"{EndMessage} ({Duration}ms) [Timing {TimingId}]","EndMessage":"Completed.","Duration":443,"TimingId":"86eb2b1","SourceContext":"Umbraco.Web.PublishedCache.NuCache.PublishedSnapshotService","ProcessId":23180,"ProcessName":"iisexpress","ThreadId":1,"AppDomainId":2,"AppDomainAppId":"LMW3SVC2ROOT","MachineName":"WKWIN4480425","Log4NetLevel":"INFO ","HttpRequestNumber":1,"HttpRequestId":"f5152d61-9d51-455c-9e1e-8b03ba11003d"}
{"@t":"2024-01-09T08:10:23.9880990Z","@mt":"Initializing Umbraco internal event handlers for cache refreshing.","SourceContext":"Umbraco.Web.Cache.DistributedCacheBinderComponent","ProcessId":23180,"ProcessName":"iisexpress","ThreadId":1,"AppDomainId":2,"AppDomainAppId":"LMW3SVC2ROOT","MachineName":"WKWIN4480425","Log4NetLevel":"INFO ","HttpRequestNumber":1,"HttpRequestId":"f5152d61-9d51-455c-9e1e-8b03ba11003d"}
{"@t":"2024-01-09T08:10:24.1190591Z","@mt":"Adding examine event handlers for {RegisteredIndexers} index providers.","RegisteredIndexers":3,"SourceContext":"Umbraco.Web.Search.ExamineComponent","ProcessId":23180,"ProcessName":"iisexpress","ThreadId":1,"AppDomainId":2,"AppDomainAppId":"LMW3SVC2ROOT","MachineName":"WKWIN4480425","Log4NetLevel":"INFO ","HttpRequestNumber":1,"HttpRequestId":"f5152d61-9d51-455c-9e1e-8b03ba11003d"}
{"@t":"2024-01-09T08:10:30.5400822Z","@mt":"Starting '{MigrationName}'...","MigrationName":"Skybrud.Umbraco.Redirects","SourceContext":"Umbraco.Core.Migrations.MigrationPlan","ProcessId":23180,"ProcessName":"iisexpress","ThreadId":1,"AppDomainId":2,"AppDomainAppId":"LMW3SVC2ROOT","MachineName":"WKWIN4480425","Log4NetLevel":"INFO ","HttpRequestNumber":1,"HttpRequestId":"f5152d61-9d51-455c-9e1e-8b03ba11003d"}
{"@t":"2024-01-09T08:10:30.5410809Z","@mt":"At {OrigState}","OrigState":"2.1.1","SourceContext":"Umbraco.Core.Migrations.MigrationPlan","ProcessId":23180,"ProcessName":"iisexpress","ThreadId":1,"AppDomainId":2,"AppDomainAppId":"LMW3SVC2ROOT","MachineName":"WKWIN4480425","Log4NetLevel":"INFO ","HttpRequestNumber":1,"HttpRequestId":"f5152d61-9d51-455c-9e1e-8b03ba11003d"}
{"@t":"2024-01-09T08:10:30.5430753Z","@mt":"Done (pending scope completion).","SourceContext":"Umbraco.Core.Migrations.MigrationPlan","ProcessId":23180,"ProcessName":"iisexpress","ThreadId":1,"AppDomainId":2,"AppDomainAppId":"LMW3SVC2ROOT","MachineName":"WKWIN4480425","Log4NetLevel":"INFO ","HttpRequestNumber":1,"HttpRequestId":"f5152d61-9d51-455c-9e1e-8b03ba11003d"}
{"@t":"2024-01-09T08:10:30.5690057Z","@mt":"Starting initialize async background thread.","SourceContext":"Umbraco.Web.Search.BackgroundIndexRebuilder","ProcessId":23180,"ProcessName":"iisexpress","ThreadId":1,"AppDomainId":2,"AppDomainAppId":"LMW3SVC2ROOT","MachineName":"WKWIN4480425","Log4NetLevel":"INFO ","HttpRequestNumber":1,"HttpRequestId":"f5152d61-9d51-455c-9e1e-8b03ba11003d"}
{"@t":"2024-01-09T08:10:30.5759868Z","@mt":"{EndMessage} ({Duration}ms) [Timing {TimingId}]","EndMessage":"Booted.","Duration":13250,"TimingId":"c56b684","SourceContext":"Umbraco.Core.Runtime.CoreRuntime","ProcessId":23180,"ProcessName":"iisexpress","ThreadId":1,"AppDomainId":2,"AppDomainAppId":"LMW3SVC2ROOT","MachineName":"WKWIN4480425","Log4NetLevel":"INFO ","HttpRequestNumber":1,"HttpRequestId":"f5152d61-9d51-455c-9e1e-8b03ba11003d"}
{"@t":"2024-01-09T08:10:31.4177564Z","@mt":"New url {Url} detected, re-discovering application url.","Url":"http://localhost/umbraco","SourceContext":"Umbraco.Core.Sync.ApplicationUrlHelper","ProcessId":23180,"ProcessName":"iisexpress","ThreadId":6,"AppDomainId":2,"AppDomainAppId":"LMW3SVC2ROOT","MachineName":"WKWIN4480425","Log4NetLevel":"INFO ","HttpRequestNumber":2,"HttpRequestId":"ac8738bf-c996-4d99-a083-af2df2ebde92"}
{"@t":"2024-01-09T08:10:31.4207487Z","@mt":"ApplicationUrl: {UmbracoAppUrl} (UmbracoModule request)","UmbracoAppUrl":"http://localhost/umbraco","SourceContext":"Umbraco.Core.Sync.ApplicationUrlHelper","ProcessId":23180,"ProcessName":"iisexpress","ThreadId":6,"AppDomainId":2,"AppDomainAppId":"LMW3SVC2ROOT","MachineName":"WKWIN4480425","Log4NetLevel":"INFO ","HttpRequestNumber":2,"HttpRequestId":"ac8738bf-c996-4d99-a083-af2df2ebde92"}
{"@t":"2024-01-09T08:10:34.8890482Z","@mt":"The current Document Type {ContentTypeAlias} matches a locally declared controller of type {ControllerName}. Custom Controllers for Umbraco routing must implement '{UmbracoRenderController}' and inherit from '{UmbracoControllerBase}'.","@l":"Warning","ContentTypeAlias":"home","ControllerName":"HPPlc.Controllers.HomeController","UmbracoRenderController":"Umbraco.Web.Mvc.IRenderController","UmbracoControllerBase":"System.Web.Mvc.ControllerBase","SourceContext":"Umbraco.Web.Mvc.RenderRouteHandler","ProcessId":23180,"ProcessName":"iisexpress","ThreadId":6,"AppDomainId":2,"AppDomainAppId":"LMW3SVC2ROOT","MachineName":"WKWIN4480425","Log4NetLevel":"WARN ","HttpRequestNumber":2,"HttpRequestId":"ac8738bf-c996-4d99-a083-af2df2ebde92"}
{"@t":"2024-01-09T08:13:43.5761286Z","@mt":"{StartMessage} [Timing {TimingId}]","StartMessage":"Booting Umbraco 8.12.2.","TimingId":"3fa4b2f","SourceContext":"Umbraco.Core.Runtime.CoreRuntime","ProcessId":31144,"ProcessName":"iisexpress","ThreadId":1,"AppDomainId":2,"AppDomainAppId":"LMW3SVC2ROOT","MachineName":"WKWIN4480425","Log4NetLevel":"INFO ","HttpRequestNumber":1,"HttpRequestId":"e8745d18-6976-4f82-938b-049b1970ff71"}
{"@t":"2024-01-09T08:13:43.5950784Z","@mt":"Booting site '{HostingSiteName}', app '{HostingApplicationID}', path '{HostingPhysicalPath}', server '{MachineName}'.","HostingSiteName":"HPPlc","HostingApplicationID":"/LM/W3SVC/2/ROOT","HostingPhysicalPath":"C:\\Projects\\HP Proj\\HP PLC\\Preprod\\HPPlc_PreProd_Index_BW\\HPPlc\\","MachineName":"WKWIN4480425","SourceContext":"Umbraco.Core.Runtime.CoreRuntime","ProcessId":31144,"ProcessName":"iisexpress","ThreadId":1,"AppDomainId":2,"AppDomainAppId":"LMW3SVC2ROOT","Log4NetLevel":"INFO ","HttpRequestNumber":1,"HttpRequestId":"e8745d18-6976-4f82-938b-049b1970ff71"}
{"@t":"2024-01-09T08:13:43.6652439Z","@mt":"Acquiring.","SourceContext":"Umbraco.Core.Runtime.MainDom","ProcessId":31144,"ProcessName":"iisexpress","ThreadId":1,"AppDomainId":2,"AppDomainAppId":"LMW3SVC2ROOT","MachineName":"WKWIN4480425","Log4NetLevel":"INFO ","HttpRequestNumber":1,"HttpRequestId":"e8745d18-6976-4f82-938b-049b1970ff71"}
{"@t":"2024-01-09T08:13:43.6662414Z","@mt":"Acquired.","SourceContext":"Umbraco.Core.Runtime.MainDom","ProcessId":31144,"ProcessName":"iisexpress","ThreadId":1,"AppDomainId":2,"AppDomainAppId":"LMW3SVC2ROOT","MachineName":"WKWIN4480425","Log4NetLevel":"INFO ","HttpRequestNumber":1,"HttpRequestId":"e8745d18-6976-4f82-938b-049b1970ff71"}
{"@t":"2024-01-09T08:13:44.7568565Z","@mt":"{StartMessage} [Timing {TimingId}]","StartMessage":"Resolving composer types.","TimingId":"f9dad1e","SourceContext":"Umbraco.Core.Runtime.CoreRuntime","ProcessId":31144,"ProcessName":"iisexpress","ThreadId":1,"AppDomainId":2,"AppDomainAppId":"LMW3SVC2ROOT","MachineName":"WKWIN4480425","Log4NetLevel":"INFO ","HttpRequestNumber":1,"HttpRequestId":"e8745d18-6976-4f82-938b-049b1970ff71"}
{"@t":"2024-01-09T08:13:44.9593150Z","@mt":"{EndMessage} ({Duration}ms) [Timing {TimingId}]","EndMessage":"Resolved.","Duration":201,"TimingId":"f9dad1e","SourceContext":"Umbraco.Core.Runtime.CoreRuntime","ProcessId":31144,"ProcessName":"iisexpress","ThreadId":1,"AppDomainId":2,"AppDomainAppId":"LMW3SVC2ROOT","MachineName":"WKWIN4480425","Log4NetLevel":"INFO ","HttpRequestNumber":1,"HttpRequestId":"e8745d18-6976-4f82-938b-049b1970ff71"}
{"@t":"2024-01-09T08:13:45.6686522Z","@mt":"Registered with MainDom, localContentDbExists? {LocalContentDbExists}, localMediaDbExists? {LocalMediaDbExists}","LocalContentDbExists":true,"LocalMediaDbExists":true,"SourceContext":"Umbraco.Web.PublishedCache.NuCache.PublishedSnapshotService","ProcessId":31144,"ProcessName":"iisexpress","ThreadId":1,"AppDomainId":2,"AppDomainAppId":"LMW3SVC2ROOT","MachineName":"WKWIN4480425","Log4NetLevel":"INFO ","HttpRequestNumber":1,"HttpRequestId":"e8745d18-6976-4f82-938b-049b1970ff71"}
{"@t":"2024-01-09T08:13:45.6686522Z","@mt":"Creating the content store, localContentDbExists? {LocalContentDbExists}","LocalContentDbExists":true,"SourceContext":"Umbraco.Web.PublishedCache.NuCache.PublishedSnapshotService","ProcessId":31144,"ProcessName":"iisexpress","ThreadId":1,"AppDomainId":2,"AppDomainAppId":"LMW3SVC2ROOT","MachineName":"WKWIN4480425","Log4NetLevel":"INFO ","HttpRequestNumber":1,"HttpRequestId":"e8745d18-6976-4f82-938b-049b1970ff71"}
{"@t":"2024-01-09T08:13:45.6706482Z","@mt":"Creating the media store, localMediaDbExists? {LocalMediaDbExists}","LocalMediaDbExists":true,"SourceContext":"Umbraco.Web.PublishedCache.NuCache.PublishedSnapshotService","ProcessId":31144,"ProcessName":"iisexpress","ThreadId":1,"AppDomainId":2,"AppDomainAppId":"LMW3SVC2ROOT","MachineName":"WKWIN4480425","Log4NetLevel":"INFO ","HttpRequestNumber":1,"HttpRequestId":"e8745d18-6976-4f82-938b-049b1970ff71"}
{"@t":"2024-01-09T08:13:46.0792352Z","@mt":"{StartMessage} [Timing {TimingId}]","StartMessage":"Loading content from local cache file","TimingId":"daa981f","SourceContext":"Umbraco.Web.PublishedCache.NuCache.PublishedSnapshotService","ProcessId":31144,"ProcessName":"iisexpress","ThreadId":1,"AppDomainId":2,"AppDomainAppId":"LMW3SVC2ROOT","MachineName":"WKWIN4480425","Log4NetLevel":"INFO ","HttpRequestNumber":1,"HttpRequestId":"e8745d18-6976-4f82-938b-049b1970ff71"}
{"@t":"2024-01-09T08:13:46.6387717Z","@mt":"{EndMessage} ({Duration}ms) [Timing {TimingId}]","EndMessage":"Completed.","Duration":559,"TimingId":"daa981f","SourceContext":"Umbraco.Web.PublishedCache.NuCache.PublishedSnapshotService","ProcessId":31144,"ProcessName":"iisexpress","ThreadId":1,"AppDomainId":2,"AppDomainAppId":"LMW3SVC2ROOT","MachineName":"WKWIN4480425","Log4NetLevel":"INFO ","HttpRequestNumber":1,"HttpRequestId":"e8745d18-6976-4f82-938b-049b1970ff71"}
{"@t":"2024-01-09T08:13:46.6501181Z","@mt":"{StartMessage} [Timing {TimingId}]","StartMessage":"Loading media from local cache file","TimingId":"f451cd5","SourceContext":"Umbraco.Web.PublishedCache.NuCache.PublishedSnapshotService","ProcessId":31144,"ProcessName":"iisexpress","ThreadId":1,"AppDomainId":2,"AppDomainAppId":"LMW3SVC2ROOT","MachineName":"WKWIN4480425","Log4NetLevel":"INFO ","HttpRequestNumber":1,"HttpRequestId":"e8745d18-6976-4f82-938b-049b1970ff71"}
{"@t":"2024-01-09T08:13:46.8625499Z","@mt":"{EndMessage} ({Duration}ms) [Timing {TimingId}]","EndMessage":"Completed.","Duration":212,"TimingId":"f451cd5","SourceContext":"Umbraco.Web.PublishedCache.NuCache.PublishedSnapshotService","ProcessId":31144,"ProcessName":"iisexpress","ThreadId":1,"AppDomainId":2,"AppDomainAppId":"LMW3SVC2ROOT","MachineName":"WKWIN4480425","Log4NetLevel":"INFO ","HttpRequestNumber":1,"HttpRequestId":"e8745d18-6976-4f82-938b-049b1970ff71"}
{"@t":"2024-01-09T08:13:47.1132410Z","@mt":"Initializing Umbraco internal event handlers for cache refreshing.","SourceContext":"Umbraco.Web.Cache.DistributedCacheBinderComponent","ProcessId":31144,"ProcessName":"iisexpress","ThreadId":1,"AppDomainId":2,"AppDomainAppId":"LMW3SVC2ROOT","MachineName":"WKWIN4480425","Log4NetLevel":"INFO ","HttpRequestNumber":1,"HttpRequestId":"e8745d18-6976-4f82-938b-049b1970ff71"}
{"@t":"2024-01-09T08:13:47.1871905Z","@mt":"Adding examine event handlers for {RegisteredIndexers} index providers.","RegisteredIndexers":3,"SourceContext":"Umbraco.Web.Search.ExamineComponent","ProcessId":31144,"ProcessName":"iisexpress","ThreadId":1,"AppDomainId":2,"AppDomainAppId":"LMW3SVC2ROOT","MachineName":"WKWIN4480425","Log4NetLevel":"INFO ","HttpRequestNumber":1,"HttpRequestId":"e8745d18-6976-4f82-938b-049b1970ff71"}
{"@t":"2024-01-09T08:13:49.9379717Z","@mt":"Starting '{MigrationName}'...","MigrationName":"Skybrud.Umbraco.Redirects","SourceContext":"Umbraco.Core.Migrations.MigrationPlan","ProcessId":31144,"ProcessName":"iisexpress","ThreadId":1,"AppDomainId":2,"AppDomainAppId":"LMW3SVC2ROOT","MachineName":"WKWIN4480425","Log4NetLevel":"INFO ","HttpRequestNumber":1,"HttpRequestId":"e8745d18-6976-4f82-938b-049b1970ff71"}
{"@t":"2024-01-09T08:13:49.9379717Z","@mt":"At {OrigState}","OrigState":"2.1.1","SourceContext":"Umbraco.Core.Migrations.MigrationPlan","ProcessId":31144,"ProcessName":"iisexpress","ThreadId":1,"AppDomainId":2,"AppDomainAppId":"LMW3SVC2ROOT","MachineName":"WKWIN4480425","Log4NetLevel":"INFO ","HttpRequestNumber":1,"HttpRequestId":"e8745d18-6976-4f82-938b-049b1970ff71"}
{"@t":"2024-01-09T08:13:49.9379717Z","@mt":"Done (pending scope completion).","SourceContext":"Umbraco.Core.Migrations.MigrationPlan","ProcessId":31144,"ProcessName":"iisexpress","ThreadId":1,"AppDomainId":2,"AppDomainAppId":"LMW3SVC2ROOT","MachineName":"WKWIN4480425","Log4NetLevel":"INFO ","HttpRequestNumber":1,"HttpRequestId":"e8745d18-6976-4f82-938b-049b1970ff71"}
{"@t":"2024-01-09T08:13:49.9419610Z","@mt":"Starting initialize async background thread.","SourceContext":"Umbraco.Web.Search.BackgroundIndexRebuilder","ProcessId":31144,"ProcessName":"iisexpress","ThreadId":1,"AppDomainId":2,"AppDomainAppId":"LMW3SVC2ROOT","MachineName":"WKWIN4480425","Log4NetLevel":"INFO ","HttpRequestNumber":1,"HttpRequestId":"e8745d18-6976-4f82-938b-049b1970ff71"}
{"@t":"2024-01-09T08:13:49.9439565Z","@mt":"{EndMessage} ({Duration}ms) [Timing {TimingId}]","EndMessage":"Booted.","Duration":6374,"TimingId":"3fa4b2f","SourceContext":"Umbraco.Core.Runtime.CoreRuntime","ProcessId":31144,"ProcessName":"iisexpress","ThreadId":1,"AppDomainId":2,"AppDomainAppId":"LMW3SVC2ROOT","MachineName":"WKWIN4480425","Log4NetLevel":"INFO ","HttpRequestNumber":1,"HttpRequestId":"e8745d18-6976-4f82-938b-049b1970ff71"}
{"@t":"2024-01-09T08:13:50.1940071Z","@mt":"New url {Url} detected, re-discovering application url.","Url":"http://localhost/umbraco","SourceContext":"Umbraco.Core.Sync.ApplicationUrlHelper","ProcessId":31144,"ProcessName":"iisexpress","ThreadId":6,"AppDomainId":2,"AppDomainAppId":"LMW3SVC2ROOT","MachineName":"WKWIN4480425","Log4NetLevel":"INFO ","HttpRequestNumber":2,"HttpRequestId":"210142ba-dca6-4a84-8db8-8973b846e2f9"}
{"@t":"2024-01-09T08:13:50.1959635Z","@mt":"ApplicationUrl: {UmbracoAppUrl} (UmbracoModule request)","UmbracoAppUrl":"http://localhost/umbraco","SourceContext":"Umbraco.Core.Sync.ApplicationUrlHelper","ProcessId":31144,"ProcessName":"iisexpress","ThreadId":6,"AppDomainId":2,"AppDomainAppId":"LMW3SVC2ROOT","MachineName":"WKWIN4480425","Log4NetLevel":"INFO ","HttpRequestNumber":2,"HttpRequestId":"210142ba-dca6-4a84-8db8-8973b846e2f9"}
{"@t":"2024-01-09T08:13:51.2776894Z","@mt":"The current Document Type {ContentTypeAlias} matches a locally declared controller of type {ControllerName}. Custom Controllers for Umbraco routing must implement '{UmbracoRenderController}' and inherit from '{UmbracoControllerBase}'.","@l":"Warning","ContentTypeAlias":"home","ControllerName":"HPPlc.Controllers.HomeController","UmbracoRenderController":"Umbraco.Web.Mvc.IRenderController","UmbracoControllerBase":"System.Web.Mvc.ControllerBase","SourceContext":"Umbraco.Web.Mvc.RenderRouteHandler","ProcessId":31144,"ProcessName":"iisexpress","ThreadId":6,"AppDomainId":2,"AppDomainAppId":"LMW3SVC2ROOT","MachineName":"WKWIN4480425","Log4NetLevel":"WARN ","HttpRequestNumber":2,"HttpRequestId":"210142ba-dca6-4a84-8db8-8973b846e2f9"}
{"@t":"2024-01-09T14:04:52.2737874Z","@mt":"{StartMessage} [Timing {TimingId}]","StartMessage":"Booting Umbraco 8.12.2.","TimingId":"f0355cd","SourceContext":"Umbraco.Core.Runtime.CoreRuntime","ProcessId":34592,"ProcessName":"iisexpress","ThreadId":1,"AppDomainId":2,"AppDomainAppId":"LMW3SVC2ROOT","MachineName":"WKWIN4480425","Log4NetLevel":"INFO ","HttpRequestNumber":1,"HttpRequestId":"e8c3723d-9c33-4839-8c88-9875bc4f6ff4"}
{"@t":"2024-01-09T14:04:52.2957290Z","@mt":"Booting site '{HostingSiteName}', app '{HostingApplicationID}', path '{HostingPhysicalPath}', server '{MachineName}'.","HostingSiteName":"HPPlc","HostingApplicationID":"/LM/W3SVC/2/ROOT","HostingPhysicalPath":"C:\\Projects\\HP Proj\\HP PLC\\Preprod\\HPPlc_PreProd_Index_BW\\HPPlc\\","MachineName":"WKWIN4480425","SourceContext":"Umbraco.Core.Runtime.CoreRuntime","ProcessId":34592,"ProcessName":"iisexpress","ThreadId":1,"AppDomainId":2,"AppDomainAppId":"LMW3SVC2ROOT","Log4NetLevel":"INFO ","HttpRequestNumber":1,"HttpRequestId":"e8c3723d-9c33-4839-8c88-9875bc4f6ff4"}
{"@t":"2024-01-09T14:04:52.4045507Z","@mt":"Acquiring.","SourceContext":"Umbraco.Core.Runtime.MainDom","ProcessId":34592,"ProcessName":"iisexpress","ThreadId":1,"AppDomainId":2,"AppDomainAppId":"LMW3SVC2ROOT","MachineName":"WKWIN4480425","Log4NetLevel":"INFO ","HttpRequestNumber":1,"HttpRequestId":"e8c3723d-9c33-4839-8c88-9875bc4f6ff4"}
{"@t":"2024-01-09T14:04:52.4055861Z","@mt":"Acquired.","SourceContext":"Umbraco.Core.Runtime.MainDom","ProcessId":34592,"ProcessName":"iisexpress","ThreadId":1,"AppDomainId":2,"AppDomainAppId":"LMW3SVC2ROOT","MachineName":"WKWIN4480425","Log4NetLevel":"INFO ","HttpRequestNumber":1,"HttpRequestId":"e8c3723d-9c33-4839-8c88-9875bc4f6ff4"}
{"@t":"2024-01-09T14:04:53.5095419Z","@mt":"{StartMessage} [Timing {TimingId}]","StartMessage":"Resolving composer types.","TimingId":"186deed","SourceContext":"Umbraco.Core.Runtime.CoreRuntime","ProcessId":34592,"ProcessName":"iisexpress","ThreadId":1,"AppDomainId":2,"AppDomainAppId":"LMW3SVC2ROOT","MachineName":"WKWIN4480425","Log4NetLevel":"INFO ","HttpRequestNumber":1,"HttpRequestId":"e8c3723d-9c33-4839-8c88-9875bc4f6ff4"}
{"@t":"2024-01-09T14:04:53.7190424Z","@mt":"{EndMessage} ({Duration}ms) [Timing {TimingId}]","EndMessage":"Resolved.","Duration":208,"TimingId":"186deed","SourceContext":"Umbraco.Core.Runtime.CoreRuntime","ProcessId":34592,"ProcessName":"iisexpress","ThreadId":1,"AppDomainId":2,"AppDomainAppId":"LMW3SVC2ROOT","MachineName":"WKWIN4480425","Log4NetLevel":"INFO ","HttpRequestNumber":1,"HttpRequestId":"e8c3723d-9c33-4839-8c88-9875bc4f6ff4"}
{"@t":"2024-01-09T14:04:54.4962726Z","@mt":"Registered with MainDom, localContentDbExists? {LocalContentDbExists}, localMediaDbExists? {LocalMediaDbExists}","LocalContentDbExists":true,"LocalMediaDbExists":true,"SourceContext":"Umbraco.Web.PublishedCache.NuCache.PublishedSnapshotService","ProcessId":34592,"ProcessName":"iisexpress","ThreadId":1,"AppDomainId":2,"AppDomainAppId":"LMW3SVC2ROOT","MachineName":"WKWIN4480425","Log4NetLevel":"INFO ","HttpRequestNumber":1,"HttpRequestId":"e8c3723d-9c33-4839-8c88-9875bc4f6ff4"}
{"@t":"2024-01-09T14:04:54.4962726Z","@mt":"Creating the content store, localContentDbExists? {LocalContentDbExists}","LocalContentDbExists":true,"SourceContext":"Umbraco.Web.PublishedCache.NuCache.PublishedSnapshotService","ProcessId":34592,"ProcessName":"iisexpress","ThreadId":1,"AppDomainId":2,"AppDomainAppId":"LMW3SVC2ROOT","MachineName":"WKWIN4480425","Log4NetLevel":"INFO ","HttpRequestNumber":1,"HttpRequestId":"e8c3723d-9c33-4839-8c88-9875bc4f6ff4"}
{"@t":"2024-01-09T14:04:54.4982676Z","@mt":"Creating the media store, localMediaDbExists? {LocalMediaDbExists}","LocalMediaDbExists":true,"SourceContext":"Umbraco.Web.PublishedCache.NuCache.PublishedSnapshotService","ProcessId":34592,"ProcessName":"iisexpress","ThreadId":1,"AppDomainId":2,"AppDomainAppId":"LMW3SVC2ROOT","MachineName":"WKWIN4480425","Log4NetLevel":"INFO ","HttpRequestNumber":1,"HttpRequestId":"e8c3723d-9c33-4839-8c88-9875bc4f6ff4"}
{"@t":"2024-01-09T14:04:54.9745386Z","@mt":"{StartMessage} [Timing {TimingId}]","StartMessage":"Loading content from local cache file","TimingId":"d8e48fc","SourceContext":"Umbraco.Web.PublishedCache.NuCache.PublishedSnapshotService","ProcessId":34592,"ProcessName":"iisexpress","ThreadId":1,"AppDomainId":2,"AppDomainAppId":"LMW3SVC2ROOT","MachineName":"WKWIN4480425","Log4NetLevel":"INFO ","HttpRequestNumber":1,"HttpRequestId":"e8c3723d-9c33-4839-8c88-9875bc4f6ff4"}
{"@t":"2024-01-09T14:04:55.7634923Z","@mt":"{EndMessage} ({Duration}ms) [Timing {TimingId}]","EndMessage":"Completed.","Duration":789,"TimingId":"d8e48fc","SourceContext":"Umbraco.Web.PublishedCache.NuCache.PublishedSnapshotService","ProcessId":34592,"ProcessName":"iisexpress","ThreadId":1,"AppDomainId":2,"AppDomainAppId":"LMW3SVC2ROOT","MachineName":"WKWIN4480425","Log4NetLevel":"INFO ","HttpRequestNumber":1,"HttpRequestId":"e8c3723d-9c33-4839-8c88-9875bc4f6ff4"}
{"@t":"2024-01-09T14:04:55.7768056Z","@mt":"{StartMessage} [Timing {TimingId}]","StartMessage":"Loading media from local cache file","TimingId":"2168ffb","SourceContext":"Umbraco.Web.PublishedCache.NuCache.PublishedSnapshotService","ProcessId":34592,"ProcessName":"iisexpress","ThreadId":1,"AppDomainId":2,"AppDomainAppId":"LMW3SVC2ROOT","MachineName":"WKWIN4480425","Log4NetLevel":"INFO ","HttpRequestNumber":1,"HttpRequestId":"e8c3723d-9c33-4839-8c88-9875bc4f6ff4"}
{"@t":"2024-01-09T14:04:56.0751052Z","@mt":"{EndMessage} ({Duration}ms) [Timing {TimingId}]","EndMessage":"Completed.","Duration":298,"TimingId":"2168ffb","SourceContext":"Umbraco.Web.PublishedCache.NuCache.PublishedSnapshotService","ProcessId":34592,"ProcessName":"iisexpress","ThreadId":1,"AppDomainId":2,"AppDomainAppId":"LMW3SVC2ROOT","MachineName":"WKWIN4480425","Log4NetLevel":"INFO ","HttpRequestNumber":1,"HttpRequestId":"e8c3723d-9c33-4839-8c88-9875bc4f6ff4"}
{"@t":"2024-01-09T14:04:56.3444942Z","@mt":"Initializing Umbraco internal event handlers for cache refreshing.","SourceContext":"Umbraco.Web.Cache.DistributedCacheBinderComponent","ProcessId":34592,"ProcessName":"iisexpress","ThreadId":1,"AppDomainId":2,"AppDomainAppId":"LMW3SVC2ROOT","MachineName":"WKWIN4480425","Log4NetLevel":"INFO ","HttpRequestNumber":1,"HttpRequestId":"e8c3723d-9c33-4839-8c88-9875bc4f6ff4"}
{"@t":"2024-01-09T14:04:56.4288303Z","@mt":"Adding examine event handlers for {RegisteredIndexers} index providers.","RegisteredIndexers":3,"SourceContext":"Umbraco.Web.Search.ExamineComponent","ProcessId":34592,"ProcessName":"iisexpress","ThreadId":1,"AppDomainId":2,"AppDomainAppId":"LMW3SVC2ROOT","MachineName":"WKWIN4480425","Log4NetLevel":"INFO ","HttpRequestNumber":1,"HttpRequestId":"e8c3723d-9c33-4839-8c88-9875bc4f6ff4"}
{"@t":"2024-01-09T14:04:59.3228353Z","@mt":"Starting '{MigrationName}'...","MigrationName":"Skybrud.Umbraco.Redirects","SourceContext":"Umbraco.Core.Migrations.MigrationPlan","ProcessId":34592,"ProcessName":"iisexpress","ThreadId":1,"AppDomainId":2,"AppDomainAppId":"LMW3SVC2ROOT","MachineName":"WKWIN4480425","Log4NetLevel":"INFO ","HttpRequestNumber":1,"HttpRequestId":"e8c3723d-9c33-4839-8c88-9875bc4f6ff4"}
{"@t":"2024-01-09T14:04:59.3228353Z","@mt":"At {OrigState}","OrigState":"2.1.1","SourceContext":"Umbraco.Core.Migrations.MigrationPlan","ProcessId":34592,"ProcessName":"iisexpress","ThreadId":1,"AppDomainId":2,"AppDomainAppId":"LMW3SVC2ROOT","MachineName":"WKWIN4480425","Log4NetLevel":"INFO ","HttpRequestNumber":1,"HttpRequestId":"e8c3723d-9c33-4839-8c88-9875bc4f6ff4"}
{"@t":"2024-01-09T14:04:59.3228353Z","@mt":"Done (pending scope completion).","SourceContext":"Umbraco.Core.Migrations.MigrationPlan","ProcessId":34592,"ProcessName":"iisexpress","ThreadId":1,"AppDomainId":2,"AppDomainAppId":"LMW3SVC2ROOT","MachineName":"WKWIN4480425","Log4NetLevel":"INFO ","HttpRequestNumber":1,"HttpRequestId":"e8c3723d-9c33-4839-8c88-9875bc4f6ff4"}
{"@t":"2024-01-09T14:04:59.3318113Z","@mt":"Starting initialize async background thread.","SourceContext":"Umbraco.Web.Search.BackgroundIndexRebuilder","ProcessId":34592,"ProcessName":"iisexpress","ThreadId":1,"AppDomainId":2,"AppDomainAppId":"LMW3SVC2ROOT","MachineName":"WKWIN4480425","Log4NetLevel":"INFO ","HttpRequestNumber":1,"HttpRequestId":"e8c3723d-9c33-4839-8c88-9875bc4f6ff4"}
{"@t":"2024-01-09T14:04:59.3338057Z","@mt":"{EndMessage} ({Duration}ms) [Timing {TimingId}]","EndMessage":"Booted.","Duration":7067,"TimingId":"f0355cd","SourceContext":"Umbraco.Core.Runtime.CoreRuntime","ProcessId":34592,"ProcessName":"iisexpress","ThreadId":1,"AppDomainId":2,"AppDomainAppId":"LMW3SVC2ROOT","MachineName":"WKWIN4480425","Log4NetLevel":"INFO ","HttpRequestNumber":1,"HttpRequestId":"e8c3723d-9c33-4839-8c88-9875bc4f6ff4"}
{"@t":"2024-01-09T14:04:59.6190262Z","@mt":"New url {Url} detected, re-discovering application url.","Url":"http://localhost/umbraco","SourceContext":"Umbraco.Core.Sync.ApplicationUrlHelper","ProcessId":34592,"ProcessName":"iisexpress","ThreadId":6,"AppDomainId":2,"AppDomainAppId":"LMW3SVC2ROOT","MachineName":"WKWIN4480425","Log4NetLevel":"INFO ","HttpRequestNumber":2,"HttpRequestId":"cf037d8c-1032-4307-98a2-4c6b2e0a979b"}
{"@t":"2024-01-09T14:04:59.6200234Z","@mt":"ApplicationUrl: {UmbracoAppUrl} (UmbracoModule request)","UmbracoAppUrl":"http://localhost/umbraco","SourceContext":"Umbraco.Core.Sync.ApplicationUrlHelper","ProcessId":34592,"ProcessName":"iisexpress","ThreadId":6,"AppDomainId":2,"AppDomainAppId":"LMW3SVC2ROOT","MachineName":"WKWIN4480425","Log4NetLevel":"INFO ","HttpRequestNumber":2,"HttpRequestId":"cf037d8c-1032-4307-98a2-4c6b2e0a979b"}
{"@t":"2024-01-09T14:05:00.7562817Z","@mt":"The current Document Type {ContentTypeAlias} matches a locally declared controller of type {ControllerName}. Custom Controllers for Umbraco routing must implement '{UmbracoRenderController}' and inherit from '{UmbracoControllerBase}'.","@l":"Warning","ContentTypeAlias":"home","ControllerName":"HPPlc.Controllers.HomeController","UmbracoRenderController":"Umbraco.Web.Mvc.IRenderController","UmbracoControllerBase":"System.Web.Mvc.ControllerBase","SourceContext":"Umbraco.Web.Mvc.RenderRouteHandler","ProcessId":34592,"ProcessName":"iisexpress","ThreadId":6,"AppDomainId":2,"AppDomainAppId":"LMW3SVC2ROOT","MachineName":"WKWIN4480425","Log4NetLevel":"WARN ","HttpRequestNumber":2,"HttpRequestId":"cf037d8c-1032-4307-98a2-4c6b2e0a979b"}
