{"@t":"2022-09-29T11:10:52.7451512Z","@mt":"{StartMessage} [Timing {TimingId}]","StartMessage":"Booting Umbraco 8.12.2.","TimingId":"d1b4787","SourceContext":"Umbraco.Core.Runtime.CoreRuntime","ProcessId":30196,"ProcessName":"iisexpress","ThreadId":1,"AppDomainId":2,"AppDomainAppId":"LMW3SVC2ROOT","MachineName":"WKWIN4480425","Log4NetLevel":"INFO ","HttpRequestNumber":1,"HttpRequestId":"5f458152-c545-4e0a-856f-5cd75d59c1ea"}
{"@t":"2022-09-29T11:10:52.7980118Z","@mt":"Booting site '{HostingSiteName}', app '{HostingApplicationID}', path '{HostingPhysicalPath}', server '{MachineName}'.","HostingSiteName":"HPPlc","HostingApplicationID":"/LM/W3SVC/2/ROOT","HostingPhysicalPath":"C:\\Projects\\HP Proj\\HP PLC\\Preprod\\HPPlc_PreProd_Index\\HPPlc\\","MachineName":"WKWIN4480425","SourceContext":"Umbraco.Core.Runtime.CoreRuntime","ProcessId":30196,"ProcessName":"iisexpress","ThreadId":1,"AppDomainId":2,"AppDomainAppId":"LMW3SVC2ROOT","Log4NetLevel":"INFO ","HttpRequestNumber":1,"HttpRequestId":"5f458152-c545-4e0a-856f-5cd75d59c1ea"}
{"@t":"2022-09-29T11:10:53.0762671Z","@mt":"Acquiring.","SourceContext":"Umbraco.Core.Runtime.MainDom","ProcessId":30196,"ProcessName":"iisexpress","ThreadId":1,"AppDomainId":2,"AppDomainAppId":"LMW3SVC2ROOT","MachineName":"WKWIN4480425","Log4NetLevel":"INFO ","HttpRequestNumber":1,"HttpRequestId":"5f458152-c545-4e0a-856f-5cd75d59c1ea"}
{"@t":"2022-09-29T11:10:53.0942190Z","@mt":"Acquired.","SourceContext":"Umbraco.Core.Runtime.MainDom","ProcessId":30196,"ProcessName":"iisexpress","ThreadId":1,"AppDomainId":2,"AppDomainAppId":"LMW3SVC2ROOT","MachineName":"WKWIN4480425","Log4NetLevel":"INFO ","HttpRequestNumber":1,"HttpRequestId":"5f458152-c545-4e0a-856f-5cd75d59c1ea"}
{"@t":"2022-09-29T11:11:03.8246280Z","@mt":"{StartMessage} [Timing {TimingId}]","StartMessage":"Resolving composer types.","TimingId":"c4e923c","SourceContext":"Umbraco.Core.Runtime.CoreRuntime","ProcessId":30196,"ProcessName":"iisexpress","ThreadId":1,"AppDomainId":2,"AppDomainAppId":"LMW3SVC2ROOT","MachineName":"WKWIN4480425","Log4NetLevel":"INFO ","HttpRequestNumber":1,"HttpRequestId":"5f458152-c545-4e0a-856f-5cd75d59c1ea"}
{"@t":"2022-09-29T11:11:03.8824743Z","@mt":"{EndMessage} ({Duration}ms) [Timing {TimingId}]","EndMessage":"Resolved.","Duration":56,"TimingId":"c4e923c","SourceContext":"Umbraco.Core.Runtime.CoreRuntime","ProcessId":30196,"ProcessName":"iisexpress","ThreadId":1,"AppDomainId":2,"AppDomainAppId":"LMW3SVC2ROOT","MachineName":"WKWIN4480425","Log4NetLevel":"INFO ","HttpRequestNumber":1,"HttpRequestId":"5f458152-c545-4e0a-856f-5cd75d59c1ea"}
{"@t":"2022-09-29T11:11:06.1377791Z","@mt":"Registered with MainDom, localContentDbExists? {LocalContentDbExists}, localMediaDbExists? {LocalMediaDbExists}","LocalContentDbExists":true,"LocalMediaDbExists":true,"SourceContext":"Umbraco.Web.PublishedCache.NuCache.PublishedSnapshotService","ProcessId":30196,"ProcessName":"iisexpress","ThreadId":1,"AppDomainId":2,"AppDomainAppId":"LMW3SVC2ROOT","MachineName":"WKWIN4480425","Log4NetLevel":"INFO ","HttpRequestNumber":1,"HttpRequestId":"5f458152-c545-4e0a-856f-5cd75d59c1ea"}
{"@t":"2022-09-29T11:11:06.1377791Z","@mt":"Creating the content store, localContentDbExists? {LocalContentDbExists}","LocalContentDbExists":true,"SourceContext":"Umbraco.Web.PublishedCache.NuCache.PublishedSnapshotService","ProcessId":30196,"ProcessName":"iisexpress","ThreadId":1,"AppDomainId":2,"AppDomainAppId":"LMW3SVC2ROOT","MachineName":"WKWIN4480425","Log4NetLevel":"INFO ","HttpRequestNumber":1,"HttpRequestId":"5f458152-c545-4e0a-856f-5cd75d59c1ea"}
{"@t":"2022-09-29T11:11:06.1427639Z","@mt":"Creating the media store, localMediaDbExists? {LocalMediaDbExists}","LocalMediaDbExists":true,"SourceContext":"Umbraco.Web.PublishedCache.NuCache.PublishedSnapshotService","ProcessId":30196,"ProcessName":"iisexpress","ThreadId":1,"AppDomainId":2,"AppDomainAppId":"LMW3SVC2ROOT","MachineName":"WKWIN4480425","Log4NetLevel":"INFO ","HttpRequestNumber":1,"HttpRequestId":"5f458152-c545-4e0a-856f-5cd75d59c1ea"}
{"@t":"2022-09-29T11:11:37.2613331Z","@mt":"{StartMessage} [Timing {TimingId}]","StartMessage":"Loading content from local cache file","TimingId":"c4ce758","SourceContext":"Umbraco.Web.PublishedCache.NuCache.PublishedSnapshotService","ProcessId":30196,"ProcessName":"iisexpress","ThreadId":1,"AppDomainId":2,"AppDomainAppId":"LMW3SVC2ROOT","MachineName":"WKWIN4480425","Log4NetLevel":"INFO ","HttpRequestNumber":1,"HttpRequestId":"5f458152-c545-4e0a-856f-5cd75d59c1ea"}
{"@t":"2022-09-29T11:11:37.2922518Z","@mt":"Tried to load content from the local cache file but it was empty.","SourceContext":"Umbraco.Web.PublishedCache.NuCache.PublishedSnapshotService","ProcessId":30196,"ProcessName":"iisexpress","ThreadId":1,"AppDomainId":2,"AppDomainAppId":"LMW3SVC2ROOT","MachineName":"WKWIN4480425","Log4NetLevel":"INFO ","HttpRequestNumber":1,"HttpRequestId":"5f458152-c545-4e0a-856f-5cd75d59c1ea"}
{"@t":"2022-09-29T11:11:37.2922518Z","@mt":"{EndMessage} ({Duration}ms) [Timing {TimingId}]","EndMessage":"Completed.","Duration":30,"TimingId":"c4ce758","SourceContext":"Umbraco.Web.PublishedCache.NuCache.PublishedSnapshotService","ProcessId":30196,"ProcessName":"iisexpress","ThreadId":1,"AppDomainId":2,"AppDomainAppId":"LMW3SVC2ROOT","MachineName":"WKWIN4480425","Log4NetLevel":"INFO ","HttpRequestNumber":1,"HttpRequestId":"5f458152-c545-4e0a-856f-5cd75d59c1ea"}
{"@t":"2022-09-29T11:11:37.3082108Z","@mt":"Loading content from local db raised warnings, will reload from database.","@l":"Warning","SourceContext":"Umbraco.Web.PublishedCache.NuCache.PublishedSnapshotService","ProcessId":30196,"ProcessName":"iisexpress","ThreadId":1,"AppDomainId":2,"AppDomainAppId":"LMW3SVC2ROOT","MachineName":"WKWIN4480425","Log4NetLevel":"WARN ","HttpRequestNumber":1,"HttpRequestId":"5f458152-c545-4e0a-856f-5cd75d59c1ea"}
{"@t":"2022-09-29T11:11:37.3520944Z","@mt":"{StartMessage} [Timing {TimingId}]","StartMessage":"Loading media from local cache file","TimingId":"7b6d001","SourceContext":"Umbraco.Web.PublishedCache.NuCache.PublishedSnapshotService","ProcessId":30196,"ProcessName":"iisexpress","ThreadId":1,"AppDomainId":2,"AppDomainAppId":"LMW3SVC2ROOT","MachineName":"WKWIN4480425","Log4NetLevel":"INFO ","HttpRequestNumber":1,"HttpRequestId":"5f458152-c545-4e0a-856f-5cd75d59c1ea"}
{"@t":"2022-09-29T11:11:37.5266269Z","@mt":"{EndMessage} ({Duration}ms) [Timing {TimingId}]","EndMessage":"Completed.","Duration":174,"TimingId":"7b6d001","SourceContext":"Umbraco.Web.PublishedCache.NuCache.PublishedSnapshotService","ProcessId":30196,"ProcessName":"iisexpress","ThreadId":1,"AppDomainId":2,"AppDomainAppId":"LMW3SVC2ROOT","MachineName":"WKWIN4480425","Log4NetLevel":"INFO ","HttpRequestNumber":1,"HttpRequestId":"5f458152-c545-4e0a-856f-5cd75d59c1ea"}
{"@t":"2022-09-29T11:11:37.5814779Z","@mt":"{StartMessage} [Timing {TimingId}]","StartMessage":"Loading content from database","TimingId":"4f9b265","SourceContext":"Umbraco.Web.PublishedCache.NuCache.PublishedSnapshotService","ProcessId":30196,"ProcessName":"iisexpress","ThreadId":1,"AppDomainId":2,"AppDomainAppId":"LMW3SVC2ROOT","MachineName":"WKWIN4480425","Log4NetLevel":"INFO ","HttpRequestNumber":1,"HttpRequestId":"5f458152-c545-4e0a-856f-5cd75d59c1ea"}
{"@t":"2022-09-29T11:12:10.5410562Z","@mt":"Exception ({InstanceId}).","@l":"Error","@x":"System.Data.SqlClient.SqlException (0x80131904): Execution Timeout Expired.  The timeout period elapsed prior to completion of the operation or the server is not responding. ---> System.ComponentModel.Win32Exception (0x80004005): The wait operation timed out\r\n   at System.Data.SqlClient.SqlConnection.OnError(SqlException exception, Boolean breakConnection, Action`1 wrapCloseInAction)\r\n   at System.Data.SqlClient.SqlInternalConnection.OnError(SqlException exception, Boolean breakConnection, Action`1 wrapCloseInAction)\r\n   at System.Data.SqlClient.TdsParser.ThrowExceptionAndWarning(TdsParserStateObject stateObj, Boolean callerHasConnectionLock, Boolean asyncClose)\r\n   at System.Data.SqlClient.TdsParser.TryRun(RunBehavior runBehavior, SqlCommand cmdHandler, SqlDataReader dataStream, BulkCopySimpleResultSet bulkCopyHandler, TdsParserStateObject stateObj, Boolean& dataReady)\r\n   at System.Data.SqlClient.SqlDataReader.TrySetMetaData(_SqlMetaDataSet metaData, Boolean moreInfo)\r\n   at System.Data.SqlClient.TdsParser.TryRun(RunBehavior runBehavior, SqlCommand cmdHandler, SqlDataReader dataStream, BulkCopySimpleResultSet bulkCopyHandler, TdsParserStateObject stateObj, Boolean& dataReady)\r\n   at System.Data.SqlClient.SqlDataReader.TryConsumeMetaData()\r\n   at System.Data.SqlClient.SqlDataReader.get_MetaData()\r\n   at System.Data.SqlClient.SqlCommand.FinishExecuteReader(SqlDataReader ds, RunBehavior runBehavior, String resetOptionsString, Boolean isInternal, Boolean forDescribeParameterEncryption, Boolean shouldCacheForAlwaysEncrypted)\r\n   at System.Data.SqlClient.SqlCommand.RunExecuteReaderTds(CommandBehavior cmdBehavior, RunBehavior runBehavior, Boolean returnStream, Boolean async, Int32 timeout, Task& task, Boolean asyncWrite, Boolean inRetry, SqlDataReader ds, Boolean describeParameterEncryptionRequest)\r\n   at System.Data.SqlClient.SqlCommand.RunExecuteReader(CommandBehavior cmdBehavior, RunBehavior runBehavior, Boolean returnStream, String method, TaskCompletionSource`1 completion, Int32 timeout, Task& task, Boolean& usedCache, Boolean asyncWrite, Boolean inRetry)\r\n   at System.Data.SqlClient.SqlCommand.RunExecuteReader(CommandBehavior cmdBehavior, RunBehavior runBehavior, Boolean returnStream, String method)\r\n   at System.Data.SqlClient.SqlCommand.ExecuteReader(CommandBehavior behavior, String method)\r\n   at System.Data.SqlClient.SqlCommand.ExecuteDbDataReader(CommandBehavior behavior)\r\n   at System.Data.Common.DbCommand.ExecuteReader(CommandBehavior behavior)\r\n   at StackExchange.Profiling.Data.ProfiledDbCommand.ExecuteDbDataReader(CommandBehavior behavior) in C:\\projects\\dotnet\\src\\MiniProfiler.Shared\\Data\\ProfiledDbCommand.cs:line 221\r\n   at System.Data.Common.DbCommand.ExecuteReader(CommandBehavior behavior)\r\n   at Umbraco.Core.Persistence.FaultHandling.FaultHandlingDbCommand.<>c__DisplayClass30_0.<ExecuteDbDataReader>b__0() in D:\\a\\1\\s\\src\\Umbraco.Core\\Persistence\\FaultHandling\\RetryDbConnection.cs:line 204\r\n   at Umbraco.Core.Persistence.FaultHandling.FaultHandlingDbCommand.<>c__DisplayClass33_0`1.<Execute>b__0() in D:\\a\\1\\s\\src\\Umbraco.Core\\Persistence\\FaultHandling\\RetryDbConnection.cs:line 222\r\n   at Umbraco.Core.Persistence.FaultHandling.RetryPolicy.ExecuteAction[TResult](Func`1 func) in D:\\a\\1\\s\\src\\Umbraco.Core\\Persistence\\FaultHandling\\RetryPolicy.cs:line 172\r\n   at Umbraco.Core.Persistence.FaultHandling.FaultHandlingDbCommand.Execute[T](Func`1 f) in D:\\a\\1\\s\\src\\Umbraco.Core\\Persistence\\FaultHandling\\RetryDbConnection.cs:line 219\r\n   at Umbraco.Core.Persistence.FaultHandling.FaultHandlingDbCommand.ExecuteDbDataReader(CommandBehavior behavior) in D:\\a\\1\\s\\src\\Umbraco.Core\\Persistence\\FaultHandling\\RetryDbConnection.cs:line 204\r\n   at System.Data.Common.DbCommand.ExecuteReader()\r\n   at NPoco.Database.ExecuteReaderHelper(DbCommand cmd)\r\n   at NPoco.Database.ExecuteDataReader(DbCommand cmd)\r\nClientConnectionId:570e6f5a-e065-4be7-9ddc-336cbbe6de76\r\nError Number:-2,State:0,Class:11","InstanceId":"8df4d96c","SourceContext":"Umbraco.Core.Persistence.UmbracoDatabase","ProcessId":30196,"ProcessName":"iisexpress","ThreadId":1,"AppDomainId":2,"AppDomainAppId":"LMW3SVC2ROOT","MachineName":"WKWIN4480425","Log4NetLevel":"ERROR","HttpRequestNumber":1,"HttpRequestId":"5f458152-c545-4e0a-856f-5cd75d59c1ea"}
{"@t":"2022-09-29T11:12:10.6308152Z","@mt":"{EndMessage} ({Duration}ms) [Timing {TimingId}]","EndMessage":"Completed.","Duration":33048,"TimingId":"4f9b265","SourceContext":"Umbraco.Web.PublishedCache.NuCache.PublishedSnapshotService","ProcessId":30196,"ProcessName":"iisexpress","ThreadId":1,"AppDomainId":2,"AppDomainAppId":"LMW3SVC2ROOT","MachineName":"WKWIN4480425","Log4NetLevel":"INFO ","HttpRequestNumber":1,"HttpRequestId":"5f458152-c545-4e0a-856f-5cd75d59c1ea"}
{"@t":"2022-09-29T11:18:36.9927168Z","@mt":"{StartMessage} [Timing {TimingId}]","StartMessage":"Booting Umbraco 8.12.2.","TimingId":"43c2306","SourceContext":"Umbraco.Core.Runtime.CoreRuntime","ProcessId":30936,"ProcessName":"iisexpress","ThreadId":1,"AppDomainId":2,"AppDomainAppId":"LMW3SVC2ROOT","MachineName":"WKWIN4480425","Log4NetLevel":"INFO ","HttpRequestNumber":1,"HttpRequestId":"0994b0e6-67b9-4917-9c34-abb54de9d1ed"}
{"@t":"2022-09-29T11:18:37.0286211Z","@mt":"Booting site '{HostingSiteName}', app '{HostingApplicationID}', path '{HostingPhysicalPath}', server '{MachineName}'.","HostingSiteName":"HPPlc","HostingApplicationID":"/LM/W3SVC/2/ROOT","HostingPhysicalPath":"C:\\Projects\\HP Proj\\HP PLC\\Preprod\\HPPlc_PreProd_Index\\HPPlc\\","MachineName":"WKWIN4480425","SourceContext":"Umbraco.Core.Runtime.CoreRuntime","ProcessId":30936,"ProcessName":"iisexpress","ThreadId":1,"AppDomainId":2,"AppDomainAppId":"LMW3SVC2ROOT","Log4NetLevel":"INFO ","HttpRequestNumber":1,"HttpRequestId":"0994b0e6-67b9-4917-9c34-abb54de9d1ed"}
{"@t":"2022-09-29T11:18:37.1701463Z","@mt":"Acquiring.","SourceContext":"Umbraco.Core.Runtime.MainDom","ProcessId":30936,"ProcessName":"iisexpress","ThreadId":1,"AppDomainId":2,"AppDomainAppId":"LMW3SVC2ROOT","MachineName":"WKWIN4480425","Log4NetLevel":"INFO ","HttpRequestNumber":1,"HttpRequestId":"0994b0e6-67b9-4917-9c34-abb54de9d1ed"}
{"@t":"2022-09-29T11:18:37.1741286Z","@mt":"Acquired.","SourceContext":"Umbraco.Core.Runtime.MainDom","ProcessId":30936,"ProcessName":"iisexpress","ThreadId":1,"AppDomainId":2,"AppDomainAppId":"LMW3SVC2ROOT","MachineName":"WKWIN4480425","Log4NetLevel":"INFO ","HttpRequestNumber":1,"HttpRequestId":"0994b0e6-67b9-4917-9c34-abb54de9d1ed"}
{"@t":"2022-09-29T11:18:45.1584834Z","@mt":"{StartMessage} [Timing {TimingId}]","StartMessage":"Resolving composer types.","TimingId":"4ac71b3","SourceContext":"Umbraco.Core.Runtime.CoreRuntime","ProcessId":30936,"ProcessName":"iisexpress","ThreadId":1,"AppDomainId":2,"AppDomainAppId":"LMW3SVC2ROOT","MachineName":"WKWIN4480425","Log4NetLevel":"INFO ","HttpRequestNumber":1,"HttpRequestId":"0994b0e6-67b9-4917-9c34-abb54de9d1ed"}
{"@t":"2022-09-29T11:18:45.6022979Z","@mt":"{EndMessage} ({Duration}ms) [Timing {TimingId}]","EndMessage":"Resolved.","Duration":441,"TimingId":"4ac71b3","SourceContext":"Umbraco.Core.Runtime.CoreRuntime","ProcessId":30936,"ProcessName":"iisexpress","ThreadId":1,"AppDomainId":2,"AppDomainAppId":"LMW3SVC2ROOT","MachineName":"WKWIN4480425","Log4NetLevel":"INFO ","HttpRequestNumber":1,"HttpRequestId":"0994b0e6-67b9-4917-9c34-abb54de9d1ed"}
{"@t":"2022-09-29T11:18:50.9277252Z","@mt":"Registered with MainDom, localContentDbExists? {LocalContentDbExists}, localMediaDbExists? {LocalMediaDbExists}","LocalContentDbExists":true,"LocalMediaDbExists":true,"SourceContext":"Umbraco.Web.PublishedCache.NuCache.PublishedSnapshotService","ProcessId":30936,"ProcessName":"iisexpress","ThreadId":1,"AppDomainId":2,"AppDomainAppId":"LMW3SVC2ROOT","MachineName":"WKWIN4480425","Log4NetLevel":"INFO ","HttpRequestNumber":1,"HttpRequestId":"0994b0e6-67b9-4917-9c34-abb54de9d1ed"}
{"@t":"2022-09-29T11:18:50.9277252Z","@mt":"Creating the content store, localContentDbExists? {LocalContentDbExists}","LocalContentDbExists":true,"SourceContext":"Umbraco.Web.PublishedCache.NuCache.PublishedSnapshotService","ProcessId":30936,"ProcessName":"iisexpress","ThreadId":1,"AppDomainId":2,"AppDomainAppId":"LMW3SVC2ROOT","MachineName":"WKWIN4480425","Log4NetLevel":"INFO ","HttpRequestNumber":1,"HttpRequestId":"0994b0e6-67b9-4917-9c34-abb54de9d1ed"}
{"@t":"2022-09-29T11:18:50.9307168Z","@mt":"Creating the media store, localMediaDbExists? {LocalMediaDbExists}","LocalMediaDbExists":true,"SourceContext":"Umbraco.Web.PublishedCache.NuCache.PublishedSnapshotService","ProcessId":30936,"ProcessName":"iisexpress","ThreadId":1,"AppDomainId":2,"AppDomainAppId":"LMW3SVC2ROOT","MachineName":"WKWIN4480425","Log4NetLevel":"INFO ","HttpRequestNumber":1,"HttpRequestId":"0994b0e6-67b9-4917-9c34-abb54de9d1ed"}
{"@t":"2022-09-29T11:19:17.6552925Z","@mt":"{StartMessage} [Timing {TimingId}]","StartMessage":"Loading content from local cache file","TimingId":"5048062","SourceContext":"Umbraco.Web.PublishedCache.NuCache.PublishedSnapshotService","ProcessId":30936,"ProcessName":"iisexpress","ThreadId":1,"AppDomainId":2,"AppDomainAppId":"LMW3SVC2ROOT","MachineName":"WKWIN4480425","Log4NetLevel":"INFO ","HttpRequestNumber":1,"HttpRequestId":"0994b0e6-67b9-4917-9c34-abb54de9d1ed"}
{"@t":"2022-09-29T11:19:17.6782326Z","@mt":"Tried to load content from the local cache file but it was empty.","SourceContext":"Umbraco.Web.PublishedCache.NuCache.PublishedSnapshotService","ProcessId":30936,"ProcessName":"iisexpress","ThreadId":1,"AppDomainId":2,"AppDomainAppId":"LMW3SVC2ROOT","MachineName":"WKWIN4480425","Log4NetLevel":"INFO ","HttpRequestNumber":1,"HttpRequestId":"0994b0e6-67b9-4917-9c34-abb54de9d1ed"}
{"@t":"2022-09-29T11:19:17.6782326Z","@mt":"{EndMessage} ({Duration}ms) [Timing {TimingId}]","EndMessage":"Completed.","Duration":22,"TimingId":"5048062","SourceContext":"Umbraco.Web.PublishedCache.NuCache.PublishedSnapshotService","ProcessId":30936,"ProcessName":"iisexpress","ThreadId":1,"AppDomainId":2,"AppDomainAppId":"LMW3SVC2ROOT","MachineName":"WKWIN4480425","Log4NetLevel":"INFO ","HttpRequestNumber":1,"HttpRequestId":"0994b0e6-67b9-4917-9c34-abb54de9d1ed"}
{"@t":"2022-09-29T11:19:17.6941896Z","@mt":"Loading content from local db raised warnings, will reload from database.","@l":"Warning","SourceContext":"Umbraco.Web.PublishedCache.NuCache.PublishedSnapshotService","ProcessId":30936,"ProcessName":"iisexpress","ThreadId":1,"AppDomainId":2,"AppDomainAppId":"LMW3SVC2ROOT","MachineName":"WKWIN4480425","Log4NetLevel":"WARN ","HttpRequestNumber":1,"HttpRequestId":"0994b0e6-67b9-4917-9c34-abb54de9d1ed"}
{"@t":"2022-09-29T11:19:17.7081523Z","@mt":"{StartMessage} [Timing {TimingId}]","StartMessage":"Loading media from local cache file","TimingId":"8b2f86f","SourceContext":"Umbraco.Web.PublishedCache.NuCache.PublishedSnapshotService","ProcessId":30936,"ProcessName":"iisexpress","ThreadId":1,"AppDomainId":2,"AppDomainAppId":"LMW3SVC2ROOT","MachineName":"WKWIN4480425","Log4NetLevel":"INFO ","HttpRequestNumber":1,"HttpRequestId":"0994b0e6-67b9-4917-9c34-abb54de9d1ed"}
{"@t":"2022-09-29T11:19:22.6008689Z","@mt":"{EndMessage} ({Duration}ms) [Timing {TimingId}]","EndMessage":"Completed.","Duration":4892,"TimingId":"8b2f86f","SourceContext":"Umbraco.Web.PublishedCache.NuCache.PublishedSnapshotService","ProcessId":30936,"ProcessName":"iisexpress","ThreadId":1,"AppDomainId":2,"AppDomainAppId":"LMW3SVC2ROOT","MachineName":"WKWIN4480425","Log4NetLevel":"INFO ","HttpRequestNumber":1,"HttpRequestId":"0994b0e6-67b9-4917-9c34-abb54de9d1ed"}
{"@t":"2022-09-29T11:19:22.6447525Z","@mt":"{StartMessage} [Timing {TimingId}]","StartMessage":"Loading content from database","TimingId":"4aaa7a8","SourceContext":"Umbraco.Web.PublishedCache.NuCache.PublishedSnapshotService","ProcessId":30936,"ProcessName":"iisexpress","ThreadId":1,"AppDomainId":2,"AppDomainAppId":"LMW3SVC2ROOT","MachineName":"WKWIN4480425","Log4NetLevel":"INFO ","HttpRequestNumber":1,"HttpRequestId":"0994b0e6-67b9-4917-9c34-abb54de9d1ed"}
{"@t":"2022-09-29T11:19:53.9311068Z","@mt":"Exception ({InstanceId}).","@l":"Error","@x":"System.Data.SqlClient.SqlException (0x80131904): Execution Timeout Expired.  The timeout period elapsed prior to completion of the operation or the server is not responding. ---> System.ComponentModel.Win32Exception (0x80004005): The wait operation timed out\r\n   at System.Data.SqlClient.SqlConnection.OnError(SqlException exception, Boolean breakConnection, Action`1 wrapCloseInAction)\r\n   at System.Data.SqlClient.SqlInternalConnection.OnError(SqlException exception, Boolean breakConnection, Action`1 wrapCloseInAction)\r\n   at System.Data.SqlClient.TdsParser.ThrowExceptionAndWarning(TdsParserStateObject stateObj, Boolean callerHasConnectionLock, Boolean asyncClose)\r\n   at System.Data.SqlClient.TdsParser.TryRun(RunBehavior runBehavior, SqlCommand cmdHandler, SqlDataReader dataStream, BulkCopySimpleResultSet bulkCopyHandler, TdsParserStateObject stateObj, Boolean& dataReady)\r\n   at System.Data.SqlClient.SqlDataReader.TrySetMetaData(_SqlMetaDataSet metaData, Boolean moreInfo)\r\n   at System.Data.SqlClient.TdsParser.TryRun(RunBehavior runBehavior, SqlCommand cmdHandler, SqlDataReader dataStream, BulkCopySimpleResultSet bulkCopyHandler, TdsParserStateObject stateObj, Boolean& dataReady)\r\n   at System.Data.SqlClient.SqlDataReader.TryConsumeMetaData()\r\n   at System.Data.SqlClient.SqlDataReader.get_MetaData()\r\n   at System.Data.SqlClient.SqlCommand.FinishExecuteReader(SqlDataReader ds, RunBehavior runBehavior, String resetOptionsString, Boolean isInternal, Boolean forDescribeParameterEncryption, Boolean shouldCacheForAlwaysEncrypted)\r\n   at System.Data.SqlClient.SqlCommand.RunExecuteReaderTds(CommandBehavior cmdBehavior, RunBehavior runBehavior, Boolean returnStream, Boolean async, Int32 timeout, Task& task, Boolean asyncWrite, Boolean inRetry, SqlDataReader ds, Boolean describeParameterEncryptionRequest)\r\n   at System.Data.SqlClient.SqlCommand.RunExecuteReader(CommandBehavior cmdBehavior, RunBehavior runBehavior, Boolean returnStream, String method, TaskCompletionSource`1 completion, Int32 timeout, Task& task, Boolean& usedCache, Boolean asyncWrite, Boolean inRetry)\r\n   at System.Data.SqlClient.SqlCommand.RunExecuteReader(CommandBehavior cmdBehavior, RunBehavior runBehavior, Boolean returnStream, String method)\r\n   at System.Data.SqlClient.SqlCommand.ExecuteReader(CommandBehavior behavior, String method)\r\n   at System.Data.SqlClient.SqlCommand.ExecuteDbDataReader(CommandBehavior behavior)\r\n   at System.Data.Common.DbCommand.ExecuteReader(CommandBehavior behavior)\r\n   at StackExchange.Profiling.Data.ProfiledDbCommand.ExecuteDbDataReader(CommandBehavior behavior) in C:\\projects\\dotnet\\src\\MiniProfiler.Shared\\Data\\ProfiledDbCommand.cs:line 221\r\n   at System.Data.Common.DbCommand.ExecuteReader(CommandBehavior behavior)\r\n   at Umbraco.Core.Persistence.FaultHandling.FaultHandlingDbCommand.<>c__DisplayClass30_0.<ExecuteDbDataReader>b__0() in D:\\a\\1\\s\\src\\Umbraco.Core\\Persistence\\FaultHandling\\RetryDbConnection.cs:line 204\r\n   at Umbraco.Core.Persistence.FaultHandling.FaultHandlingDbCommand.<>c__DisplayClass33_0`1.<Execute>b__0() in D:\\a\\1\\s\\src\\Umbraco.Core\\Persistence\\FaultHandling\\RetryDbConnection.cs:line 222\r\n   at Umbraco.Core.Persistence.FaultHandling.RetryPolicy.ExecuteAction[TResult](Func`1 func) in D:\\a\\1\\s\\src\\Umbraco.Core\\Persistence\\FaultHandling\\RetryPolicy.cs:line 172\r\n   at Umbraco.Core.Persistence.FaultHandling.FaultHandlingDbCommand.Execute[T](Func`1 f) in D:\\a\\1\\s\\src\\Umbraco.Core\\Persistence\\FaultHandling\\RetryDbConnection.cs:line 219\r\n   at Umbraco.Core.Persistence.FaultHandling.FaultHandlingDbCommand.ExecuteDbDataReader(CommandBehavior behavior) in D:\\a\\1\\s\\src\\Umbraco.Core\\Persistence\\FaultHandling\\RetryDbConnection.cs:line 204\r\n   at System.Data.Common.DbCommand.ExecuteReader()\r\n   at NPoco.Database.ExecuteReaderHelper(DbCommand cmd)\r\n   at NPoco.Database.ExecuteDataReader(DbCommand cmd)\r\nClientConnectionId:d0ee2334-db72-4125-8504-49dec82c7bd7\r\nError Number:-2,State:0,Class:11","InstanceId":"ce09e43e","SourceContext":"Umbraco.Core.Persistence.UmbracoDatabase","ProcessId":30936,"ProcessName":"iisexpress","ThreadId":1,"AppDomainId":2,"AppDomainAppId":"LMW3SVC2ROOT","MachineName":"WKWIN4480425","Log4NetLevel":"ERROR","HttpRequestNumber":1,"HttpRequestId":"0994b0e6-67b9-4917-9c34-abb54de9d1ed"}
{"@t":"2022-09-29T11:19:54.0537791Z","@mt":"{EndMessage} ({Duration}ms) [Timing {TimingId}]","EndMessage":"Completed.","Duration":31409,"TimingId":"4aaa7a8","SourceContext":"Umbraco.Web.PublishedCache.NuCache.PublishedSnapshotService","ProcessId":30936,"ProcessName":"iisexpress","ThreadId":1,"AppDomainId":2,"AppDomainAppId":"LMW3SVC2ROOT","MachineName":"WKWIN4480425","Log4NetLevel":"INFO ","HttpRequestNumber":1,"HttpRequestId":"0994b0e6-67b9-4917-9c34-abb54de9d1ed"}
